{
 "type": "FeatureCollection",
"features": [
{"geometry":{"coordinates":[106.482428333333,10.9716783333333],"type":"Point"},"id":0,"type":"Feature","properties":{"date":"2016-10-08 13:05:16","icon":"http://chart.apis.google.com/chart?chst=d_map_pin_letter&chld=0|FF0000|000000"}},
{"geometry":{"coordinates":[106.48302,10.9701166666667],"type":"Point"},"id":1,"type":"Feature","properties":{"date":"2016-10-08 13:05:34","icon":"http://chart.apis.google.com/chart?chst=d_map_pin_letter&chld=1|FF0000|000000"}},
{"geometry":{"coordinates":[106.48392,10.96951],"type":"Point"},"id":2,"type":"Feature","properties":{"date":"2016-10-08 13:06:04","icon":"http://chart.apis.google.com/chart?chst=d_map_pin_letter&chld=2|FF0000|000000"}},
{"geometry":{"coordinates":[106.485416666667,10.9685733333333],"type":"Point"},"id":3,"type":"Feature","properties":{"date":"2016-10-08 13:06:34","icon":"http://chart.apis.google.com/chart?chst=d_map_pin_letter&chld=3|FF0000|000000"}},
{"geometry":{"coordinates":[106.486635,10.9679983333333],"type":"Point"},"id":4,"type":"Feature","properties":{"date":"2016-10-08 13:07:04","icon":"http://chart.apis.google.com/chart?chst=d_map_pin_letter&chld=4|FF0000|000000"}},
{"geometry":{"coordinates":[106.488691666667,10.9672666666667],"type":"Point"},"id":5,"type":"Feature","properties":{"date":"2016-10-08 13:07:34","icon":"http://chart.apis.google.com/chart?chst=d_map_pin_letter&chld=5|FF0000|000000"}},
{"geometry":{"coordinates":[106.488995,10.96716],"type":"Point"},"id":6,"type":"Feature","properties":{"date":"2016-10-08 13:07:43","icon":"http://chart.apis.google.com/chart?chst=d_map_pin_letter&chld=6|FF0000|000000"}},
{"geometry":{"coordinates":[106.489121666667,10.9671183333333],"type":"Point"},"id":7,"type":"Feature","properties":{"date":"2016-10-08 13:07:49","icon":"http://chart.apis.google.com/chart?chst=d_map_pin_letter&chld=7|FF0000|000000"}},
{"geometry":{"coordinates":[106.491201666667,10.9663016666667],"type":"Point"},"id":8,"type":"Feature","properties":{"date":"2016-10-08 13:08:19","icon":"http://chart.apis.google.com/chart?chst=d_map_pin_letter&chld=8|FF0000|000000"}},
{"geometry":{"coordinates":[106.493783333333,10.9653],"type":"Point"},"id":9,"type":"Feature","properties":{"date":"2016-10-08 13:08:49","icon":"http://chart.apis.google.com/chart?chst=d_map_pin_letter&chld=9|FF0000|000000"}},
{"geometry":{"coordinates":[106.495421666667,10.9646566666667],"type":"Point"},"id":10,"type":"Feature","properties":{"date":"2016-10-08 13:09:19","icon":"http://chart.apis.google.com/chart?chst=d_map_pin_letter&chld=10|FF0000|000000"}},
{"geometry":{"coordinates":[106.495421666667,10.9646566666667],"type":"Point"},"id":11,"type":"Feature","properties":{"date":"2016-10-08 13:09:28","icon":"http://chart.apis.google.com/chart?chst=d_map_pin_letter&chld=11|FF0000|000000"}},
{"geometry":{"coordinates":[106.495546666667,10.96458],"type":"Point"},"id":12,"type":"Feature","properties":{"date":"2016-10-08 13:09:38","icon":"http://chart.apis.google.com/chart?chst=d_map_pin_letter&chld=12|FF0000|000000"}},
{"geometry":{"coordinates":[106.497371666667,10.9635316666667],"type":"Point"},"id":13,"type":"Feature","properties":{"date":"2016-10-08 13:10:08","icon":"http://chart.apis.google.com/chart?chst=d_map_pin_letter&chld=13|FF0000|000000"}},
{"geometry":{"coordinates":[106.497803333333,10.9632833333333],"type":"Point"},"id":14,"type":"Feature","properties":{"date":"2016-10-08 13:10:24","icon":"http://chart.apis.google.com/chart?chst=d_map_pin_letter&chld=14|FF0000|000000"}},
{"geometry":{"coordinates":[106.500285,10.9618633333333],"type":"Point"},"id":15,"type":"Feature","properties":{"date":"2016-10-08 13:10:54","icon":"http://chart.apis.google.com/chart?chst=d_map_pin_letter&chld=15|FF0000|000000"}},
{"geometry":{"coordinates":[106.502378333333,10.9606633333333],"type":"Point"},"id":16,"type":"Feature","properties":{"date":"2016-10-08 13:11:24","icon":"http://chart.apis.google.com/chart?chst=d_map_pin_letter&chld=16|FF0000|000000"}},
{"geometry":{"coordinates":[106.504243333333,10.95972],"type":"Point"},"id":17,"type":"Feature","properties":{"date":"2016-10-08 13:11:54","icon":"http://chart.apis.google.com/chart?chst=d_map_pin_letter&chld=17|FF0000|000000"}},
{"geometry":{"coordinates":[106.505073333333,10.9592783333333],"type":"Point"},"id":18,"type":"Feature","properties":{"date":"2016-10-08 13:12:10","icon":"http://chart.apis.google.com/chart?chst=d_map_pin_letter&chld=18|FF0000|000000"}},
{"geometry":{"coordinates":[106.505148333333,10.959235],"type":"Point"},"id":19,"type":"Feature","properties":{"date":"2016-10-08 13:12:12","icon":"http://chart.apis.google.com/chart?chst=d_map_pin_letter&chld=19|FF0000|000000"}},
{"geometry":{"coordinates":[106.507455,10.95807],"type":"Point"},"id":20,"type":"Feature","properties":{"date":"2016-10-08 13:12:42","icon":"http://chart.apis.google.com/chart?chst=d_map_pin_letter&chld=20|FF0000|000000"}},
{"geometry":{"coordinates":[106.50983,10.9568216666667],"type":"Point"},"id":21,"type":"Feature","properties":{"date":"2016-10-08 13:13:12","icon":"http://chart.apis.google.com/chart?chst=d_map_pin_letter&chld=21|FF0000|000000"}},
{"geometry":{"coordinates":[106.509928333333,10.956775],"type":"Point"},"id":22,"type":"Feature","properties":{"date":"2016-10-08 13:13:15","icon":"http://chart.apis.google.com/chart?chst=d_map_pin_letter&chld=22|FF0000|000000"}},
{"geometry":{"coordinates":[106.512068333333,10.95543],"type":"Point"},"id":23,"type":"Feature","properties":{"date":"2016-10-08 13:13:45","icon":"http://chart.apis.google.com/chart?chst=d_map_pin_letter&chld=23|FF0000|000000"}},
{"geometry":{"coordinates":[106.512435,10.9551983333333],"type":"Point"},"id":24,"type":"Feature","properties":{"date":"2016-10-08 13:13:59","icon":"http://chart.apis.google.com/chart?chst=d_map_pin_letter&chld=24|FF0000|000000"}},
{"geometry":{"coordinates":[106.51261,10.95509],"type":"Point"},"id":25,"type":"Feature","properties":{"date":"2016-10-08 13:14:09","icon":"http://chart.apis.google.com/chart?chst=d_map_pin_letter&chld=25|FF0000|000000"}},
{"geometry":{"coordinates":[106.5147,10.9536483333333],"type":"Point"},"id":26,"type":"Feature","properties":{"date":"2016-10-08 13:14:39","icon":"http://chart.apis.google.com/chart?chst=d_map_pin_letter&chld=26|FF0000|000000"}},
{"geometry":{"coordinates":[106.516778333333,10.9521966666667],"type":"Point"},"id":27,"type":"Feature","properties":{"date":"2016-10-08 13:15:09","icon":"http://chart.apis.google.com/chart?chst=d_map_pin_letter&chld=27|FF0000|000000"}},
{"geometry":{"coordinates":[106.519131666667,10.9506216666667],"type":"Point"},"id":28,"type":"Feature","properties":{"date":"2016-10-08 13:15:39","icon":"http://chart.apis.google.com/chart?chst=d_map_pin_letter&chld=28|FF0000|000000"}},
{"geometry":{"coordinates":[106.522601666667,10.9482666666667],"type":"Point"},"id":29,"type":"Feature","properties":{"date":"2016-10-08 13:16:09","icon":"http://chart.apis.google.com/chart?chst=d_map_pin_letter&chld=29|FF0000|000000"}},
{"geometry":{"coordinates":[106.523963333333,10.9473316666667],"type":"Point"},"id":30,"type":"Feature","properties":{"date":"2016-10-08 13:16:39","icon":"http://chart.apis.google.com/chart?chst=d_map_pin_letter&chld=30|FF0000|000000"}},
{"geometry":{"coordinates":[106.5269,10.9457316666667],"type":"Point"},"id":31,"type":"Feature","properties":{"date":"2016-10-08 13:17:09","icon":"http://chart.apis.google.com/chart?chst=d_map_pin_letter&chld=31|FF0000|000000"}},
{"geometry":{"coordinates":[106.530035,10.9442183333333],"type":"Point"},"id":32,"type":"Feature","properties":{"date":"2016-10-08 13:17:39","icon":"http://chart.apis.google.com/chart?chst=d_map_pin_letter&chld=32|FF0000|000000"}},
{"geometry":{"coordinates":[106.533223333333,10.9426766666667],"type":"Point"},"id":33,"type":"Feature","properties":{"date":"2016-10-08 13:18:09","icon":"http://chart.apis.google.com/chart?chst=d_map_pin_letter&chld=33|FF0000|000000"}},
{"geometry":{"coordinates":[106.536046666667,10.94131],"type":"Point"},"id":34,"type":"Feature","properties":{"date":"2016-10-08 13:18:39","icon":"http://chart.apis.google.com/chart?chst=d_map_pin_letter&chld=34|FF0000|000000"}},
{"geometry":{"coordinates":[106.538785,10.9399766666667],"type":"Point"},"id":35,"type":"Feature","properties":{"date":"2016-10-08 13:19:09","icon":"http://chart.apis.google.com/chart?chst=d_map_pin_letter&chld=35|FF0000|000000"}},
{"geometry":{"coordinates":[106.540743333333,10.9390316666667],"type":"Point"},"id":36,"type":"Feature","properties":{"date":"2016-10-08 13:19:39","icon":"http://chart.apis.google.com/chart?chst=d_map_pin_letter&chld=36|FF0000|000000"}},
{"geometry":{"coordinates":[106.540743333333,10.9390316666667],"type":"Point"},"id":37,"type":"Feature","properties":{"date":"2016-10-08 13:20:09","icon":"http://chart.apis.google.com/chart?chst=d_map_pin_letter&chld=37|FF0000|000000"}},
{"geometry":{"coordinates":[106.540836666667,10.9389816666667],"type":"Point"},"id":38,"type":"Feature","properties":{"date":"2016-10-08 13:20:24","icon":"http://chart.apis.google.com/chart?chst=d_map_pin_letter&chld=38|FF0000|000000"}},
{"geometry":{"coordinates":[106.54336,10.9377716666667],"type":"Point"},"id":39,"type":"Feature","properties":{"date":"2016-10-08 13:20:54","icon":"http://chart.apis.google.com/chart?chst=d_map_pin_letter&chld=39|FF0000|000000"}},
{"geometry":{"coordinates":[106.546885,10.93608],"type":"Point"},"id":40,"type":"Feature","properties":{"date":"2016-10-08 13:21:24","icon":"http://chart.apis.google.com/chart?chst=d_map_pin_letter&chld=40|FF0000|000000"}},
{"geometry":{"coordinates":[106.549596666667,10.934725],"type":"Point"},"id":41,"type":"Feature","properties":{"date":"2016-10-08 13:21:54","icon":"http://chart.apis.google.com/chart?chst=d_map_pin_letter&chld=41|FF0000|000000"}},
{"geometry":{"coordinates":[106.549858333333,10.9345383333333],"type":"Point"},"id":42,"type":"Feature","properties":{"date":"2016-10-08 13:22:03","icon":"http://chart.apis.google.com/chart?chst=d_map_pin_letter&chld=42|FF0000|000000"}},
{"geometry":{"coordinates":[106.54988,10.934515],"type":"Point"},"id":43,"type":"Feature","properties":{"date":"2016-10-08 13:22:09","icon":"http://chart.apis.google.com/chart?chst=d_map_pin_letter&chld=43|FF0000|000000"}},
{"geometry":{"coordinates":[106.55179,10.9331416666667],"type":"Point"},"id":44,"type":"Feature","properties":{"date":"2016-10-08 13:22:39","icon":"http://chart.apis.google.com/chart?chst=d_map_pin_letter&chld=44|FF0000|000000"}},
{"geometry":{"coordinates":[106.552775,10.9320566666667],"type":"Point"},"id":45,"type":"Feature","properties":{"date":"2016-10-08 13:22:59","icon":"http://chart.apis.google.com/chart?chst=d_map_pin_letter&chld=45|FF0000|000000"}},
{"geometry":{"coordinates":[106.552826666667,10.9319833333333],"type":"Point"},"id":46,"type":"Feature","properties":{"date":"2016-10-08 13:23:04","icon":"http://chart.apis.google.com/chart?chst=d_map_pin_letter&chld=46|FF0000|000000"}},
{"geometry":{"coordinates":[106.553681666667,10.9310916666667],"type":"Point"},"id":47,"type":"Feature","properties":{"date":"2016-10-08 13:23:27","icon":"http://chart.apis.google.com/chart?chst=d_map_pin_letter&chld=47|FF0000|000000"}},
{"geometry":{"coordinates":[106.553725,10.9310466666667],"type":"Point"},"id":48,"type":"Feature","properties":{"date":"2016-10-08 13:23:29","icon":"http://chart.apis.google.com/chart?chst=d_map_pin_letter&chld=48|FF0000|000000"}},
{"geometry":{"coordinates":[106.555773333333,10.92854],"type":"Point"},"id":49,"type":"Feature","properties":{"date":"2016-10-08 13:23:59","icon":"http://chart.apis.google.com/chart?chst=d_map_pin_letter&chld=49|FF0000|000000"}},
{"geometry":{"coordinates":[106.557271666667,10.92632],"type":"Point"},"id":50,"type":"Feature","properties":{"date":"2016-10-08 13:24:29","icon":"http://chart.apis.google.com/chart?chst=d_map_pin_letter&chld=50|FF0000|000000"}},
{"geometry":{"coordinates":[106.557271666667,10.92632],"type":"Point"},"id":51,"type":"Feature","properties":{"date":"2016-10-08 13:24:32","icon":"http://chart.apis.google.com/chart?chst=d_map_pin_letter&chld=51|FF0000|000000"}},
{"geometry":{"coordinates":[106.557338333333,10.926225],"type":"Point"},"id":52,"type":"Feature","properties":{"date":"2016-10-08 13:24:47","icon":"http://chart.apis.google.com/chart?chst=d_map_pin_letter&chld=52|FF0000|000000"}},
{"geometry":{"coordinates":[106.559208333333,10.92364],"type":"Point"},"id":53,"type":"Feature","properties":{"date":"2016-10-08 13:25:17","icon":"http://chart.apis.google.com/chart?chst=d_map_pin_letter&chld=53|FF0000|000000"}},
{"geometry":{"coordinates":[106.562186666667,10.9194116666667],"type":"Point"},"id":54,"type":"Feature","properties":{"date":"2016-10-08 13:25:47","icon":"http://chart.apis.google.com/chart?chst=d_map_pin_letter&chld=54|FF0000|000000"}},
{"geometry":{"coordinates":[106.564268333333,10.916355],"type":"Point"},"id":55,"type":"Feature","properties":{"date":"2016-10-08 13:26:13","icon":"http://chart.apis.google.com/chart?chst=d_map_pin_letter&chld=55|FF0000|000000"}},
{"geometry":{"coordinates":[106.56435,10.9162033333333],"type":"Point"},"id":56,"type":"Feature","properties":{"date":"2016-10-08 13:26:19","icon":"http://chart.apis.google.com/chart?chst=d_map_pin_letter&chld=56|FF0000|000000"}},
{"geometry":{"coordinates":[106.56435,10.9162033333333],"type":"Point"},"id":57,"type":"Feature","properties":{"date":"2016-10-08 13:26:22","icon":"http://chart.apis.google.com/chart?chst=d_map_pin_letter&chld=57|FF0000|000000"}},
{"geometry":{"coordinates":[106.56441,10.9161216666667],"type":"Point"},"id":58,"type":"Feature","properties":{"date":"2016-10-08 13:26:24","icon":"http://chart.apis.google.com/chart?chst=d_map_pin_letter&chld=58|FF0000|000000"}},
{"geometry":{"coordinates":[106.566218333333,10.91357],"type":"Point"},"id":59,"type":"Feature","properties":{"date":"2016-10-08 13:26:54","icon":"http://chart.apis.google.com/chart?chst=d_map_pin_letter&chld=59|FF0000|000000"}},
{"geometry":{"coordinates":[106.56874,10.9099966666667],"type":"Point"},"id":60,"type":"Feature","properties":{"date":"2016-10-08 13:27:24","icon":"http://chart.apis.google.com/chart?chst=d_map_pin_letter&chld=60|FF0000|000000"}},
{"geometry":{"coordinates":[106.571376666667,10.9062383333333],"type":"Point"},"id":61,"type":"Feature","properties":{"date":"2016-10-08 13:27:54","icon":"http://chart.apis.google.com/chart?chst=d_map_pin_letter&chld=61|FF0000|000000"}},
{"geometry":{"coordinates":[106.57318,10.9036466666667],"type":"Point"},"id":62,"type":"Feature","properties":{"date":"2016-10-08 13:28:24","icon":"http://chart.apis.google.com/chart?chst=d_map_pin_letter&chld=62|FF0000|000000"}},
{"geometry":{"coordinates":[106.574801666667,10.9013016666667],"type":"Point"},"id":63,"type":"Feature","properties":{"date":"2016-10-08 13:28:54","icon":"http://chart.apis.google.com/chart?chst=d_map_pin_letter&chld=63|FF0000|000000"}},
{"geometry":{"coordinates":[106.575685,10.8999983333333],"type":"Point"},"id":64,"type":"Feature","properties":{"date":"2016-10-08 13:29:24","icon":"http://chart.apis.google.com/chart?chst=d_map_pin_letter&chld=64|FF0000|000000"}},
{"geometry":{"coordinates":[106.577558333333,10.8973966666667],"type":"Point"},"id":65,"type":"Feature","properties":{"date":"2016-10-08 13:29:54","icon":"http://chart.apis.google.com/chart?chst=d_map_pin_letter&chld=65|FF0000|000000"}},
{"geometry":{"coordinates":[106.579285,10.8949383333333],"type":"Point"},"id":66,"type":"Feature","properties":{"date":"2016-10-08 13:30:24","icon":"http://chart.apis.google.com/chart?chst=d_map_pin_letter&chld=66|FF0000|000000"}},
{"geometry":{"coordinates":[106.580995,10.892415],"type":"Point"},"id":67,"type":"Feature","properties":{"date":"2016-10-08 13:30:54","icon":"http://chart.apis.google.com/chart?chst=d_map_pin_letter&chld=67|FF0000|000000"}},
{"geometry":{"coordinates":[106.581125,10.8922033333333],"type":"Point"},"id":68,"type":"Feature","properties":{"date":"2016-10-08 13:31:03","icon":"http://chart.apis.google.com/chart?chst=d_map_pin_letter&chld=68|FF0000|000000"}},
{"geometry":{"coordinates":[106.5812,10.8920816666667],"type":"Point"},"id":69,"type":"Feature","properties":{"date":"2016-10-08 13:31:09","icon":"http://chart.apis.google.com/chart?chst=d_map_pin_letter&chld=69|FF0000|000000"}},
{"geometry":{"coordinates":[106.58304,10.8894616666667],"type":"Point"},"id":70,"type":"Feature","properties":{"date":"2016-10-08 13:31:39","icon":"http://chart.apis.google.com/chart?chst=d_map_pin_letter&chld=70|FF0000|000000"}},
{"geometry":{"coordinates":[106.583903333333,10.888195],"type":"Point"},"id":71,"type":"Feature","properties":{"date":"2016-10-08 13:31:57","icon":"http://chart.apis.google.com/chart?chst=d_map_pin_letter&chld=71|FF0000|000000"}},
{"geometry":{"coordinates":[106.583996666667,10.8880733333333],"type":"Point"},"id":72,"type":"Feature","properties":{"date":"2016-10-08 13:32:07","icon":"http://chart.apis.google.com/chart?chst=d_map_pin_letter&chld=72|FF0000|000000"}},
{"geometry":{"coordinates":[106.585786666667,10.8856083333333],"type":"Point"},"id":73,"type":"Feature","properties":{"date":"2016-10-08 13:32:37","icon":"http://chart.apis.google.com/chart?chst=d_map_pin_letter&chld=73|FF0000|000000"}},
{"geometry":{"coordinates":[106.586333333333,10.8849166666667],"type":"Point"},"id":74,"type":"Feature","properties":{"date":"2016-10-08 13:33:02","icon":"http://chart.apis.google.com/chart?chst=d_map_pin_letter&chld=74|FF0000|000000"}},
{"geometry":{"coordinates":[106.586411666667,10.8847866666667],"type":"Point"},"id":75,"type":"Feature","properties":{"date":"2016-10-08 13:33:22","icon":"http://chart.apis.google.com/chart?chst=d_map_pin_letter&chld=75|FF0000|000000"}},
{"geometry":{"coordinates":[106.58737,10.88327],"type":"Point"},"id":76,"type":"Feature","properties":{"date":"2016-10-08 13:33:52","icon":"http://chart.apis.google.com/chart?chst=d_map_pin_letter&chld=76|FF0000|000000"}},
{"geometry":{"coordinates":[106.58737,10.88327],"type":"Point"},"id":77,"type":"Feature","properties":{"date":"2016-10-08 13:33:53","icon":"http://chart.apis.google.com/chart?chst=d_map_pin_letter&chld=77|FF0000|000000"}},
{"geometry":{"coordinates":[106.587448333333,10.8831883333333],"type":"Point"},"id":78,"type":"Feature","properties":{"date":"2016-10-08 13:33:59","icon":"http://chart.apis.google.com/chart?chst=d_map_pin_letter&chld=78|FF0000|000000"}},
{"geometry":{"coordinates":[106.589215,10.880755],"type":"Point"},"id":79,"type":"Feature","properties":{"date":"2016-10-08 13:34:29","icon":"http://chart.apis.google.com/chart?chst=d_map_pin_letter&chld=79|FF0000|000000"}},
{"geometry":{"coordinates":[106.590706666667,10.8785683333333],"type":"Point"},"id":80,"type":"Feature","properties":{"date":"2016-10-08 13:34:59","icon":"http://chart.apis.google.com/chart?chst=d_map_pin_letter&chld=80|FF0000|000000"}},
{"geometry":{"coordinates":[106.591033333333,10.87808],"type":"Point"},"id":81,"type":"Feature","properties":{"date":"2016-10-08 13:35:21","icon":"http://chart.apis.google.com/chart?chst=d_map_pin_letter&chld=81|FF0000|000000"}},
{"geometry":{"coordinates":[106.591033333333,10.87808],"type":"Point"},"id":82,"type":"Feature","properties":{"date":"2016-10-08 13:35:51","icon":"http://chart.apis.google.com/chart?chst=d_map_pin_letter&chld=82|FF0000|000000"}},
{"geometry":{"coordinates":[106.591115,10.8779933333333],"type":"Point"},"id":83,"type":"Feature","properties":{"date":"2016-10-08 13:35:52","icon":"http://chart.apis.google.com/chart?chst=d_map_pin_letter&chld=83|FF0000|000000"}},
{"geometry":{"coordinates":[106.592868333333,10.8755833333333],"type":"Point"},"id":84,"type":"Feature","properties":{"date":"2016-10-08 13:36:22","icon":"http://chart.apis.google.com/chart?chst=d_map_pin_letter&chld=84|FF0000|000000"}},
{"geometry":{"coordinates":[106.595435,10.8719766666667],"type":"Point"},"id":85,"type":"Feature","properties":{"date":"2016-10-08 13:36:52","icon":"http://chart.apis.google.com/chart?chst=d_map_pin_letter&chld=85|FF0000|000000"}},
{"geometry":{"coordinates":[106.597365,10.8692333333333],"type":"Point"},"id":86,"type":"Feature","properties":{"date":"2016-10-08 13:37:22","icon":"http://chart.apis.google.com/chart?chst=d_map_pin_letter&chld=86|FF0000|000000"}},
{"geometry":{"coordinates":[106.599513333333,10.8662133333333],"type":"Point"},"id":87,"type":"Feature","properties":{"date":"2016-10-08 13:37:52","icon":"http://chart.apis.google.com/chart?chst=d_map_pin_letter&chld=87|FF0000|000000"}},
{"geometry":{"coordinates":[106.601651666667,10.8631983333333],"type":"Point"},"id":88,"type":"Feature","properties":{"date":"2016-10-08 13:38:22","icon":"http://chart.apis.google.com/chart?chst=d_map_pin_letter&chld=88|FF0000|000000"}},
{"geometry":{"coordinates":[106.60284,10.8615183333333],"type":"Point"},"id":89,"type":"Feature","properties":{"date":"2016-10-08 13:38:52","icon":"http://chart.apis.google.com/chart?chst=d_map_pin_letter&chld=89|FF0000|000000"}},
{"geometry":{"coordinates":[106.603491666667,10.8605483333333],"type":"Point"},"id":90,"type":"Feature","properties":{"date":"2016-10-08 13:39:12","icon":"http://chart.apis.google.com/chart?chst=d_map_pin_letter&chld=90|FF0000|000000"}},
{"geometry":{"coordinates":[106.603575,10.8604616666667],"type":"Point"},"id":91,"type":"Feature","properties":{"date":"2016-10-08 13:39:17","icon":"http://chart.apis.google.com/chart?chst=d_map_pin_letter&chld=91|FF0000|000000"}},
{"geometry":{"coordinates":[106.605183333333,10.8581833333333],"type":"Point"},"id":92,"type":"Feature","properties":{"date":"2016-10-08 13:39:47","icon":"http://chart.apis.google.com/chart?chst=d_map_pin_letter&chld=92|FF0000|000000"}},
{"geometry":{"coordinates":[106.606438333333,10.856325],"type":"Point"},"id":93,"type":"Feature","properties":{"date":"2016-10-08 13:40:17","icon":"http://chart.apis.google.com/chart?chst=d_map_pin_letter&chld=93|FF0000|000000"}},
{"geometry":{"coordinates":[106.606598333333,10.8560616666667],"type":"Point"},"id":94,"type":"Feature","properties":{"date":"2016-10-08 13:40:28","icon":"http://chart.apis.google.com/chart?chst=d_map_pin_letter&chld=94|FF0000|000000"}},
{"geometry":{"coordinates":[106.606781666667,10.8557766666667],"type":"Point"},"id":95,"type":"Feature","properties":{"date":"2016-10-08 13:40:51","icon":"http://chart.apis.google.com/chart?chst=d_map_pin_letter&chld=95|FF0000|000000"}},
{"geometry":{"coordinates":[106.6075,10.8547333333333],"type":"Point"},"id":96,"type":"Feature","properties":{"date":"2016-10-08 13:41:21","icon":"http://chart.apis.google.com/chart?chst=d_map_pin_letter&chld=96|FF0000|000000"}},
{"geometry":{"coordinates":[106.609046666667,10.8523666666667],"type":"Point"},"id":97,"type":"Feature","properties":{"date":"2016-10-08 13:41:51","icon":"http://chart.apis.google.com/chart?chst=d_map_pin_letter&chld=97|FF0000|000000"}},
{"geometry":{"coordinates":[106.610713333333,10.84978],"type":"Point"},"id":98,"type":"Feature","properties":{"date":"2016-10-08 13:42:21","icon":"http://chart.apis.google.com/chart?chst=d_map_pin_letter&chld=98|FF0000|000000"}},
{"geometry":{"coordinates":[106.611676666667,10.8483],"type":"Point"},"id":99,"type":"Feature","properties":{"date":"2016-10-08 13:42:51","icon":"http://chart.apis.google.com/chart?chst=d_map_pin_letter&chld=99|FF0000|000000"}},
{"geometry":{"coordinates":[106.612593333333,10.84685],"type":"Point"},"id":100,"type":"Feature","properties":{"date":"2016-10-08 13:43:21","icon":"http://chart.apis.google.com/chart?chst=d_map_pin_letter&chld=100|FF0000|000000"}},
{"geometry":{"coordinates":[106.613643333333,10.8450833333333],"type":"Point"},"id":101,"type":"Feature","properties":{"date":"2016-10-08 13:43:51","icon":"http://chart.apis.google.com/chart?chst=d_map_pin_letter&chld=101|FF0000|000000"}},
{"geometry":{"coordinates":[106.613345,10.8431283333333],"type":"Point"},"id":102,"type":"Feature","properties":{"date":"2016-10-08 13:46:09","icon":"http://chart.apis.google.com/chart?chst=d_map_pin_letter&chld=102|FF0000|000000"}}
]}