{
 "type": "FeatureCollection",
"features": [
{"geometry":{"coordinates":[106.481826666667,10.9714383333333],"type":"Point"},"id":0,"type":"Feature","properties":{"date":"2016-09-17 13:43:23","icon":"http://chart.apis.google.com/chart?chst=d_map_pin_letter&chld=0|FF0000|000000"}},
{"geometry":{"coordinates":[106.481698333333,10.9713333333333],"type":"Point"},"id":1,"type":"Feature","properties":{"date":"2016-09-17 13:43:39","icon":"http://chart.apis.google.com/chart?chst=d_map_pin_letter&chld=1|FF0000|000000"}},
{"geometry":{"coordinates":[106.481863333333,10.97099],"type":"Point"},"id":2,"type":"Feature","properties":{"date":"2016-09-17 13:43:59","icon":"http://chart.apis.google.com/chart?chst=d_map_pin_letter&chld=2|FF0000|000000"}},
{"geometry":{"coordinates":[106.482168333333,10.9706733333333],"type":"Point"},"id":3,"type":"Feature","properties":{"date":"2016-09-17 13:44:19","icon":"http://chart.apis.google.com/chart?chst=d_map_pin_letter&chld=3|FF0000|000000"}},
{"geometry":{"coordinates":[106.48248,10.9704366666667],"type":"Point"},"id":4,"type":"Feature","properties":{"date":"2016-09-17 13:44:39","icon":"http://chart.apis.google.com/chart?chst=d_map_pin_letter&chld=4|FF0000|000000"}},
{"geometry":{"coordinates":[106.482855,10.9701733333333],"type":"Point"},"id":5,"type":"Feature","properties":{"date":"2016-09-17 13:44:59","icon":"http://chart.apis.google.com/chart?chst=d_map_pin_letter&chld=5|FF0000|000000"}},
{"geometry":{"coordinates":[106.48352,10.96975],"type":"Point"},"id":6,"type":"Feature","properties":{"date":"2016-09-17 13:45:19","icon":"http://chart.apis.google.com/chart?chst=d_map_pin_letter&chld=6|FF0000|000000"}},
{"geometry":{"coordinates":[106.484305,10.969225],"type":"Point"},"id":7,"type":"Feature","properties":{"date":"2016-09-17 13:45:39","icon":"http://chart.apis.google.com/chart?chst=d_map_pin_letter&chld=7|FF0000|000000"}},
{"geometry":{"coordinates":[106.48526,10.9686316666667],"type":"Point"},"id":8,"type":"Feature","properties":{"date":"2016-09-17 13:45:59","icon":"http://chart.apis.google.com/chart?chst=d_map_pin_letter&chld=8|FF0000|000000"}},
{"geometry":{"coordinates":[106.486041666667,10.96816],"type":"Point"},"id":9,"type":"Feature","properties":{"date":"2016-09-17 13:46:19","icon":"http://chart.apis.google.com/chart?chst=d_map_pin_letter&chld=9|FF0000|000000"}},
{"geometry":{"coordinates":[106.48718,10.9677466666667],"type":"Point"},"id":10,"type":"Feature","properties":{"date":"2016-09-17 13:46:39","icon":"http://chart.apis.google.com/chart?chst=d_map_pin_letter&chld=10|FF0000|000000"}},
{"geometry":{"coordinates":[106.488505,10.9673616666667],"type":"Point"},"id":11,"type":"Feature","properties":{"date":"2016-09-17 13:46:59","icon":"http://chart.apis.google.com/chart?chst=d_map_pin_letter&chld=11|FF0000|000000"}},
{"geometry":{"coordinates":[106.48978,10.966865],"type":"Point"},"id":12,"type":"Feature","properties":{"date":"2016-09-17 13:47:19","icon":"http://chart.apis.google.com/chart?chst=d_map_pin_letter&chld=12|FF0000|000000"}},
{"geometry":{"coordinates":[106.491285,10.9662866666667],"type":"Point"},"id":13,"type":"Feature","properties":{"date":"2016-09-17 13:47:39","icon":"http://chart.apis.google.com/chart?chst=d_map_pin_letter&chld=13|FF0000|000000"}},
{"geometry":{"coordinates":[106.492813333333,10.9656816666667],"type":"Point"},"id":14,"type":"Feature","properties":{"date":"2016-09-17 13:47:59","icon":"http://chart.apis.google.com/chart?chst=d_map_pin_letter&chld=14|FF0000|000000"}},
{"geometry":{"coordinates":[106.494216666667,10.9651266666667],"type":"Point"},"id":15,"type":"Feature","properties":{"date":"2016-09-17 13:48:19","icon":"http://chart.apis.google.com/chart?chst=d_map_pin_letter&chld=15|FF0000|000000"}},
{"geometry":{"coordinates":[106.495238333333,10.9646883333333],"type":"Point"},"id":16,"type":"Feature","properties":{"date":"2016-09-17 13:48:39","icon":"http://chart.apis.google.com/chart?chst=d_map_pin_letter&chld=16|FF0000|000000"}},
{"geometry":{"coordinates":[106.495251666667,10.9646783333333],"type":"Point"},"id":17,"type":"Feature","properties":{"date":"2016-09-17 13:48:51","icon":"http://chart.apis.google.com/chart?chst=d_map_pin_letter&chld=17|FF0000|000000"}},
{"geometry":{"coordinates":[106.495251666667,10.9646783333333],"type":"Point"},"id":18,"type":"Feature","properties":{"date":"2016-09-17 13:49:12","icon":"http://chart.apis.google.com/chart?chst=d_map_pin_letter&chld=18|FF0000|000000"}},
{"geometry":{"coordinates":[106.495423333333,10.9645866666667],"type":"Point"},"id":19,"type":"Feature","properties":{"date":"2016-09-17 13:49:18","icon":"http://chart.apis.google.com/chart?chst=d_map_pin_letter&chld=19|FF0000|000000"}},
{"geometry":{"coordinates":[106.496476666667,10.964015],"type":"Point"},"id":20,"type":"Feature","properties":{"date":"2016-09-17 13:49:38","icon":"http://chart.apis.google.com/chart?chst=d_map_pin_letter&chld=20|FF0000|000000"}},
{"geometry":{"coordinates":[106.497073333333,10.9636566666667],"type":"Point"},"id":21,"type":"Feature","properties":{"date":"2016-09-17 13:49:47","icon":"http://chart.apis.google.com/chart?chst=d_map_pin_letter&chld=21|FF0000|000000"}},
{"geometry":{"coordinates":[106.49713,10.9636233333333],"type":"Point"},"id":22,"type":"Feature","properties":{"date":"2016-09-17 13:49:48","icon":"http://chart.apis.google.com/chart?chst=d_map_pin_letter&chld=22|FF0000|000000"}},
{"geometry":{"coordinates":[106.497296666667,10.9635266666667],"type":"Point"},"id":23,"type":"Feature","properties":{"date":"2016-09-17 13:49:55","icon":"http://chart.apis.google.com/chart?chst=d_map_pin_letter&chld=23|FF0000|000000"}},
{"geometry":{"coordinates":[106.49737,10.9634933333333],"type":"Point"},"id":24,"type":"Feature","properties":{"date":"2016-09-17 13:50:06","icon":"http://chart.apis.google.com/chart?chst=d_map_pin_letter&chld=24|FF0000|000000"}},
{"geometry":{"coordinates":[106.498685,10.9627433333333],"type":"Point"},"id":25,"type":"Feature","properties":{"date":"2016-09-17 13:50:26","icon":"http://chart.apis.google.com/chart?chst=d_map_pin_letter&chld=25|FF0000|000000"}},
{"geometry":{"coordinates":[106.50098,10.9614216666667],"type":"Point"},"id":26,"type":"Feature","properties":{"date":"2016-09-17 13:50:46","icon":"http://chart.apis.google.com/chart?chst=d_map_pin_letter&chld=26|FF0000|000000"}},
{"geometry":{"coordinates":[106.502171666667,10.9607316666667],"type":"Point"},"id":27,"type":"Feature","properties":{"date":"2016-09-17 13:51:04","icon":"http://chart.apis.google.com/chart?chst=d_map_pin_letter&chld=27|FF0000|000000"}},
{"geometry":{"coordinates":[106.502171666667,10.9607316666667],"type":"Point"},"id":28,"type":"Feature","properties":{"date":"2016-09-17 13:51:24","icon":"http://chart.apis.google.com/chart?chst=d_map_pin_letter&chld=28|FF0000|000000"}},
{"geometry":{"coordinates":[106.502171666667,10.9607316666667],"type":"Point"},"id":29,"type":"Feature","properties":{"date":"2016-09-17 13:51:26","icon":"http://chart.apis.google.com/chart?chst=d_map_pin_letter&chld=29|FF0000|000000"}},
{"geometry":{"coordinates":[106.5024,10.96061],"type":"Point"},"id":30,"type":"Feature","properties":{"date":"2016-09-17 13:51:40","icon":"http://chart.apis.google.com/chart?chst=d_map_pin_letter&chld=30|FF0000|000000"}},
{"geometry":{"coordinates":[106.503183333333,10.960205],"type":"Point"},"id":31,"type":"Feature","properties":{"date":"2016-09-17 13:52:00","icon":"http://chart.apis.google.com/chart?chst=d_map_pin_letter&chld=31|FF0000|000000"}},
{"geometry":{"coordinates":[106.504856666667,10.9593583333333],"type":"Point"},"id":32,"type":"Feature","properties":{"date":"2016-09-17 13:52:20","icon":"http://chart.apis.google.com/chart?chst=d_map_pin_letter&chld=32|FF0000|000000"}},
{"geometry":{"coordinates":[106.505058333333,10.95923],"type":"Point"},"id":33,"type":"Feature","properties":{"date":"2016-09-17 13:52:27","icon":"http://chart.apis.google.com/chart?chst=d_map_pin_letter&chld=33|FF0000|000000"}},
{"geometry":{"coordinates":[106.505173333333,10.9591766666667],"type":"Point"},"id":34,"type":"Feature","properties":{"date":"2016-09-17 13:52:32","icon":"http://chart.apis.google.com/chart?chst=d_map_pin_letter&chld=34|FF0000|000000"}},
{"geometry":{"coordinates":[106.506466666667,10.9585466666667],"type":"Point"},"id":35,"type":"Feature","properties":{"date":"2016-09-17 13:52:52","icon":"http://chart.apis.google.com/chart?chst=d_map_pin_letter&chld=35|FF0000|000000"}},
{"geometry":{"coordinates":[106.508256666667,10.9576266666667],"type":"Point"},"id":36,"type":"Feature","properties":{"date":"2016-09-17 13:53:12","icon":"http://chart.apis.google.com/chart?chst=d_map_pin_letter&chld=36|FF0000|000000"}},
{"geometry":{"coordinates":[106.510008333333,10.9567066666667],"type":"Point"},"id":37,"type":"Feature","properties":{"date":"2016-09-17 13:53:32","icon":"http://chart.apis.google.com/chart?chst=d_map_pin_letter&chld=37|FF0000|000000"}},
{"geometry":{"coordinates":[106.511476666667,10.9558033333333],"type":"Point"},"id":38,"type":"Feature","properties":{"date":"2016-09-17 13:53:52","icon":"http://chart.apis.google.com/chart?chst=d_map_pin_letter&chld=38|FF0000|000000"}},
{"geometry":{"coordinates":[106.512991666667,10.9547683333333],"type":"Point"},"id":39,"type":"Feature","properties":{"date":"2016-09-17 13:54:12","icon":"http://chart.apis.google.com/chart?chst=d_map_pin_letter&chld=39|FF0000|000000"}},
{"geometry":{"coordinates":[106.514526666667,10.9537183333333],"type":"Point"},"id":40,"type":"Feature","properties":{"date":"2016-09-17 13:54:32","icon":"http://chart.apis.google.com/chart?chst=d_map_pin_letter&chld=40|FF0000|000000"}},
{"geometry":{"coordinates":[106.515368333333,10.9531216666667],"type":"Point"},"id":41,"type":"Feature","properties":{"date":"2016-09-17 13:54:47","icon":"http://chart.apis.google.com/chart?chst=d_map_pin_letter&chld=41|FF0000|000000"}},
{"geometry":{"coordinates":[106.51548,10.953045],"type":"Point"},"id":42,"type":"Feature","properties":{"date":"2016-09-17 13:54:54","icon":"http://chart.apis.google.com/chart?chst=d_map_pin_letter&chld=42|FF0000|000000"}},
{"geometry":{"coordinates":[106.516988333333,10.952045],"type":"Point"},"id":43,"type":"Feature","properties":{"date":"2016-09-17 13:55:14","icon":"http://chart.apis.google.com/chart?chst=d_map_pin_letter&chld=43|FF0000|000000"}},
{"geometry":{"coordinates":[106.518955,10.950705],"type":"Point"},"id":44,"type":"Feature","properties":{"date":"2016-09-17 13:55:34","icon":"http://chart.apis.google.com/chart?chst=d_map_pin_letter&chld=44|FF0000|000000"}},
{"geometry":{"coordinates":[106.52106,10.9492766666667],"type":"Point"},"id":45,"type":"Feature","properties":{"date":"2016-09-17 13:55:54","icon":"http://chart.apis.google.com/chart?chst=d_map_pin_letter&chld=45|FF0000|000000"}},
{"geometry":{"coordinates":[106.523083333333,10.9478816666667],"type":"Point"},"id":46,"type":"Feature","properties":{"date":"2016-09-17 13:56:14","icon":"http://chart.apis.google.com/chart?chst=d_map_pin_letter&chld=46|FF0000|000000"}},
{"geometry":{"coordinates":[106.52346,10.94763],"type":"Point"},"id":47,"type":"Feature","properties":{"date":"2016-09-17 13:56:23","icon":"http://chart.apis.google.com/chart?chst=d_map_pin_letter&chld=47|FF0000|000000"}},
{"geometry":{"coordinates":[106.52346,10.94763],"type":"Point"},"id":48,"type":"Feature","properties":{"date":"2016-09-17 13:56:43","icon":"http://chart.apis.google.com/chart?chst=d_map_pin_letter&chld=48|FF0000|000000"}},
{"geometry":{"coordinates":[106.523535,10.94756],"type":"Point"},"id":49,"type":"Feature","properties":{"date":"2016-09-17 13:56:52","icon":"http://chart.apis.google.com/chart?chst=d_map_pin_letter&chld=49|FF0000|000000"}},
{"geometry":{"coordinates":[106.524815,10.9467366666667],"type":"Point"},"id":50,"type":"Feature","properties":{"date":"2016-09-17 13:57:12","icon":"http://chart.apis.google.com/chart?chst=d_map_pin_letter&chld=50|FF0000|000000"}},
{"geometry":{"coordinates":[106.526733333333,10.9457616666667],"type":"Point"},"id":51,"type":"Feature","properties":{"date":"2016-09-17 13:57:32","icon":"http://chart.apis.google.com/chart?chst=d_map_pin_letter&chld=51|FF0000|000000"}},
{"geometry":{"coordinates":[106.528773333333,10.94478],"type":"Point"},"id":52,"type":"Feature","properties":{"date":"2016-09-17 13:57:52","icon":"http://chart.apis.google.com/chart?chst=d_map_pin_letter&chld=52|FF0000|000000"}},
{"geometry":{"coordinates":[106.530958333333,10.94373],"type":"Point"},"id":53,"type":"Feature","properties":{"date":"2016-09-17 13:58:12","icon":"http://chart.apis.google.com/chart?chst=d_map_pin_letter&chld=53|FF0000|000000"}},
{"geometry":{"coordinates":[106.532801666667,10.9428316666667],"type":"Point"},"id":54,"type":"Feature","properties":{"date":"2016-09-17 13:58:32","icon":"http://chart.apis.google.com/chart?chst=d_map_pin_letter&chld=54|FF0000|000000"}},
{"geometry":{"coordinates":[106.534596666667,10.9419683333333],"type":"Point"},"id":55,"type":"Feature","properties":{"date":"2016-09-17 13:58:52","icon":"http://chart.apis.google.com/chart?chst=d_map_pin_letter&chld=55|FF0000|000000"}},
{"geometry":{"coordinates":[106.53637,10.941105],"type":"Point"},"id":56,"type":"Feature","properties":{"date":"2016-09-17 13:59:12","icon":"http://chart.apis.google.com/chart?chst=d_map_pin_letter&chld=56|FF0000|000000"}},
{"geometry":{"coordinates":[106.53809,10.9402716666667],"type":"Point"},"id":57,"type":"Feature","properties":{"date":"2016-09-17 13:59:32","icon":"http://chart.apis.google.com/chart?chst=d_map_pin_letter&chld=57|FF0000|000000"}},
{"geometry":{"coordinates":[106.539701666667,10.9394983333333],"type":"Point"},"id":58,"type":"Feature","properties":{"date":"2016-09-17 13:59:52","icon":"http://chart.apis.google.com/chart?chst=d_map_pin_letter&chld=58|FF0000|000000"}},
{"geometry":{"coordinates":[106.54047,10.939095],"type":"Point"},"id":59,"type":"Feature","properties":{"date":"2016-09-17 14:00:12","icon":"http://chart.apis.google.com/chart?chst=d_map_pin_letter&chld=59|FF0000|000000"}},
{"geometry":{"coordinates":[106.541883333333,10.938445],"type":"Point"},"id":60,"type":"Feature","properties":{"date":"2016-09-17 14:00:32","icon":"http://chart.apis.google.com/chart?chst=d_map_pin_letter&chld=60|FF0000|000000"}},
{"geometry":{"coordinates":[106.543701666667,10.937565],"type":"Point"},"id":61,"type":"Feature","properties":{"date":"2016-09-17 14:00:52","icon":"http://chart.apis.google.com/chart?chst=d_map_pin_letter&chld=61|FF0000|000000"}},
{"geometry":{"coordinates":[106.54577,10.9365666666667],"type":"Point"},"id":62,"type":"Feature","properties":{"date":"2016-09-17 14:01:12","icon":"http://chart.apis.google.com/chart?chst=d_map_pin_letter&chld=62|FF0000|000000"}},
{"geometry":{"coordinates":[106.547808333333,10.935575],"type":"Point"},"id":63,"type":"Feature","properties":{"date":"2016-09-17 14:01:32","icon":"http://chart.apis.google.com/chart?chst=d_map_pin_letter&chld=63|FF0000|000000"}},
{"geometry":{"coordinates":[106.549301666667,10.934775],"type":"Point"},"id":64,"type":"Feature","properties":{"date":"2016-09-17 14:01:52","icon":"http://chart.apis.google.com/chart?chst=d_map_pin_letter&chld=64|FF0000|000000"}},
{"geometry":{"coordinates":[106.549848333333,10.9344966666667],"type":"Point"},"id":65,"type":"Feature","properties":{"date":"2016-09-17 14:02:04","icon":"http://chart.apis.google.com/chart?chst=d_map_pin_letter&chld=65|FF0000|000000"}},
{"geometry":{"coordinates":[106.549951666667,10.9344433333333],"type":"Point"},"id":66,"type":"Feature","properties":{"date":"2016-09-17 14:02:10","icon":"http://chart.apis.google.com/chart?chst=d_map_pin_letter&chld=66|FF0000|000000"}},
{"geometry":{"coordinates":[106.551283333333,10.93361],"type":"Point"},"id":67,"type":"Feature","properties":{"date":"2016-09-17 14:02:30","icon":"http://chart.apis.google.com/chart?chst=d_map_pin_letter&chld=67|FF0000|000000"}},
{"geometry":{"coordinates":[106.552496666667,10.9323266666667],"type":"Point"},"id":68,"type":"Feature","properties":{"date":"2016-09-17 14:02:50","icon":"http://chart.apis.google.com/chart?chst=d_map_pin_letter&chld=68|FF0000|000000"}},
{"geometry":{"coordinates":[106.552878333333,10.9318883333333],"type":"Point"},"id":69,"type":"Feature","properties":{"date":"2016-09-17 14:03:02","icon":"http://chart.apis.google.com/chart?chst=d_map_pin_letter&chld=69|FF0000|000000"}},
{"geometry":{"coordinates":[106.55294,10.9318283333333],"type":"Point"},"id":70,"type":"Feature","properties":{"date":"2016-09-17 14:03:06","icon":"http://chart.apis.google.com/chart?chst=d_map_pin_letter&chld=70|FF0000|000000"}},
{"geometry":{"coordinates":[106.554011666667,10.9306833333333],"type":"Point"},"id":71,"type":"Feature","properties":{"date":"2016-09-17 14:03:26","icon":"http://chart.apis.google.com/chart?chst=d_map_pin_letter&chld=71|FF0000|000000"}},
{"geometry":{"coordinates":[106.555481666667,10.928885],"type":"Point"},"id":72,"type":"Feature","properties":{"date":"2016-09-17 14:03:46","icon":"http://chart.apis.google.com/chart?chst=d_map_pin_letter&chld=72|FF0000|000000"}},
{"geometry":{"coordinates":[106.556216666667,10.9277966666667],"type":"Point"},"id":73,"type":"Feature","properties":{"date":"2016-09-17 14:04:06","icon":"http://chart.apis.google.com/chart?chst=d_map_pin_letter&chld=73|FF0000|000000"}},
{"geometry":{"coordinates":[106.556676666667,10.9271316666667],"type":"Point"},"id":74,"type":"Feature","properties":{"date":"2016-09-17 14:04:26","icon":"http://chart.apis.google.com/chart?chst=d_map_pin_letter&chld=74|FF0000|000000"}},
{"geometry":{"coordinates":[106.557238333333,10.9262283333333],"type":"Point"},"id":75,"type":"Feature","properties":{"date":"2016-09-17 14:04:46","icon":"http://chart.apis.google.com/chart?chst=d_map_pin_letter&chld=75|FF0000|000000"}},
{"geometry":{"coordinates":[106.557238333333,10.9262283333333],"type":"Point"},"id":76,"type":"Feature","properties":{"date":"2016-09-17 14:04:47","icon":"http://chart.apis.google.com/chart?chst=d_map_pin_letter&chld=76|FF0000|000000"}},
{"geometry":{"coordinates":[106.557301666667,10.9261516666667],"type":"Point"},"id":77,"type":"Feature","properties":{"date":"2016-09-17 14:04:53","icon":"http://chart.apis.google.com/chart?chst=d_map_pin_letter&chld=77|FF0000|000000"}},
{"geometry":{"coordinates":[106.558226666667,10.9248666666667],"type":"Point"},"id":78,"type":"Feature","properties":{"date":"2016-09-17 14:05:13","icon":"http://chart.apis.google.com/chart?chst=d_map_pin_letter&chld=78|FF0000|000000"}},
{"geometry":{"coordinates":[106.559483333333,10.9231166666667],"type":"Point"},"id":79,"type":"Feature","properties":{"date":"2016-09-17 14:05:33","icon":"http://chart.apis.google.com/chart?chst=d_map_pin_letter&chld=79|FF0000|000000"}},
{"geometry":{"coordinates":[106.561105,10.9208283333333],"type":"Point"},"id":80,"type":"Feature","properties":{"date":"2016-09-17 14:05:53","icon":"http://chart.apis.google.com/chart?chst=d_map_pin_letter&chld=80|FF0000|000000"}},
{"geometry":{"coordinates":[106.562643333333,10.918625],"type":"Point"},"id":81,"type":"Feature","properties":{"date":"2016-09-17 14:06:13","icon":"http://chart.apis.google.com/chart?chst=d_map_pin_letter&chld=81|FF0000|000000"}},
{"geometry":{"coordinates":[106.564,10.9166633333333],"type":"Point"},"id":82,"type":"Feature","properties":{"date":"2016-09-17 14:06:33","icon":"http://chart.apis.google.com/chart?chst=d_map_pin_letter&chld=82|FF0000|000000"}},
{"geometry":{"coordinates":[106.56427,10.91623],"type":"Point"},"id":83,"type":"Feature","properties":{"date":"2016-09-17 14:06:43","icon":"http://chart.apis.google.com/chart?chst=d_map_pin_letter&chld=83|FF0000|000000"}},
{"geometry":{"coordinates":[106.56435,10.9161416666667],"type":"Point"},"id":84,"type":"Feature","properties":{"date":"2016-09-17 14:06:47","icon":"http://chart.apis.google.com/chart?chst=d_map_pin_letter&chld=84|FF0000|000000"}},
{"geometry":{"coordinates":[106.565431666667,10.914595],"type":"Point"},"id":85,"type":"Feature","properties":{"date":"2016-09-17 14:07:07","icon":"http://chart.apis.google.com/chart?chst=d_map_pin_letter&chld=85|FF0000|000000"}},
{"geometry":{"coordinates":[106.567096666667,10.9122433333333],"type":"Point"},"id":86,"type":"Feature","properties":{"date":"2016-09-17 14:07:27","icon":"http://chart.apis.google.com/chart?chst=d_map_pin_letter&chld=86|FF0000|000000"}},
{"geometry":{"coordinates":[106.568901666667,10.9096733333333],"type":"Point"},"id":87,"type":"Feature","properties":{"date":"2016-09-17 14:07:47","icon":"http://chart.apis.google.com/chart?chst=d_map_pin_letter&chld=87|FF0000|000000"}},
{"geometry":{"coordinates":[106.570826666667,10.9069216666667],"type":"Point"},"id":88,"type":"Feature","properties":{"date":"2016-09-17 14:08:07","icon":"http://chart.apis.google.com/chart?chst=d_map_pin_letter&chld=88|FF0000|000000"}},
{"geometry":{"coordinates":[106.575195,10.9007433333333],"type":"Point"},"id":89,"type":"Feature","properties":{"date":"2016-09-17 14:09:07","icon":"http://chart.apis.google.com/chart?chst=d_map_pin_letter&chld=89|FF0000|000000"}},
{"geometry":{"coordinates":[106.575888333333,10.89961],"type":"Point"},"id":90,"type":"Feature","properties":{"date":"2016-09-17 14:09:28","icon":"http://chart.apis.google.com/chart?chst=d_map_pin_letter&chld=90|FF0000|000000"}},
{"geometry":{"coordinates":[106.57672,10.8983733333333],"type":"Point"},"id":91,"type":"Feature","properties":{"date":"2016-09-17 14:09:47","icon":"http://chart.apis.google.com/chart?chst=d_map_pin_letter&chld=91|FF0000|000000"}},
{"geometry":{"coordinates":[106.577983333333,10.8966483333333],"type":"Point"},"id":92,"type":"Feature","properties":{"date":"2016-09-17 14:10:08","icon":"http://chart.apis.google.com/chart?chst=d_map_pin_letter&chld=92|FF0000|000000"}},
{"geometry":{"coordinates":[106.579383333333,10.894725],"type":"Point"},"id":93,"type":"Feature","properties":{"date":"2016-09-17 14:10:28","icon":"http://chart.apis.google.com/chart?chst=d_map_pin_letter&chld=93|FF0000|000000"}},
{"geometry":{"coordinates":[106.580433333333,10.893095],"type":"Point"},"id":94,"type":"Feature","properties":{"date":"2016-09-17 14:10:48","icon":"http://chart.apis.google.com/chart?chst=d_map_pin_letter&chld=94|FF0000|000000"}},
{"geometry":{"coordinates":[106.580653333333,10.8927716666667],"type":"Point"},"id":95,"type":"Feature","properties":{"date":"2016-09-17 14:11:02","icon":"http://chart.apis.google.com/chart?chst=d_map_pin_letter&chld=95|FF0000|000000"}},
{"geometry":{"coordinates":[106.580653333333,10.8927716666667],"type":"Point"},"id":96,"type":"Feature","properties":{"date":"2016-09-17 14:11:22","icon":"http://chart.apis.google.com/chart?chst=d_map_pin_letter&chld=96|FF0000|000000"}},
{"geometry":{"coordinates":[106.580738333333,10.8926616666667],"type":"Point"},"id":97,"type":"Feature","properties":{"date":"2016-09-17 14:11:26","icon":"http://chart.apis.google.com/chart?chst=d_map_pin_letter&chld=97|FF0000|000000"}},
{"geometry":{"coordinates":[106.581545,10.8916516666667],"type":"Point"},"id":98,"type":"Feature","properties":{"date":"2016-09-17 14:11:46","icon":"http://chart.apis.google.com/chart?chst=d_map_pin_letter&chld=98|FF0000|000000"}},
{"geometry":{"coordinates":[106.582933333333,10.889705],"type":"Point"},"id":99,"type":"Feature","properties":{"date":"2016-09-17 14:12:06","icon":"http://chart.apis.google.com/chart?chst=d_map_pin_letter&chld=99|FF0000|000000"}},
{"geometry":{"coordinates":[106.58445,10.887505],"type":"Point"},"id":100,"type":"Feature","properties":{"date":"2016-09-17 14:12:26","icon":"http://chart.apis.google.com/chart?chst=d_map_pin_letter&chld=100|FF0000|000000"}},
{"geometry":{"coordinates":[106.586096666667,10.8851283333333],"type":"Point"},"id":101,"type":"Feature","properties":{"date":"2016-09-17 14:12:46","icon":"http://chart.apis.google.com/chart?chst=d_map_pin_letter&chld=101|FF0000|000000"}},
{"geometry":{"coordinates":[106.586536666667,10.8844833333333],"type":"Point"},"id":102,"type":"Feature","properties":{"date":"2016-09-17 14:13:05","icon":"http://chart.apis.google.com/chart?chst=d_map_pin_letter&chld=102|FF0000|000000"}},
{"geometry":{"coordinates":[106.586536666667,10.8844833333333],"type":"Point"},"id":103,"type":"Feature","properties":{"date":"2016-09-17 14:13:09","icon":"http://chart.apis.google.com/chart?chst=d_map_pin_letter&chld=103|FF0000|000000"}},
{"geometry":{"coordinates":[106.586536666667,10.8844833333333],"type":"Point"},"id":104,"type":"Feature","properties":{"date":"2016-09-17 14:13:10","icon":"http://chart.apis.google.com/chart?chst=d_map_pin_letter&chld=104|FF0000|000000"}},
{"geometry":{"coordinates":[106.586536666667,10.8844833333333],"type":"Point"},"id":105,"type":"Feature","properties":{"date":"2016-09-17 14:13:30","icon":"http://chart.apis.google.com/chart?chst=d_map_pin_letter&chld=105|FF0000|000000"}},
{"geometry":{"coordinates":[106.586606666667,10.884385],"type":"Point"},"id":106,"type":"Feature","properties":{"date":"2016-09-17 14:13:34","icon":"http://chart.apis.google.com/chart?chst=d_map_pin_letter&chld=106|FF0000|000000"}},
{"geometry":{"coordinates":[106.587313333333,10.883275],"type":"Point"},"id":107,"type":"Feature","properties":{"date":"2016-09-17 14:13:54","icon":"http://chart.apis.google.com/chart?chst=d_map_pin_letter&chld=107|FF0000|000000"}},
{"geometry":{"coordinates":[106.587355,10.8832183333333],"type":"Point"},"id":108,"type":"Feature","properties":{"date":"2016-09-17 14:13:59","icon":"http://chart.apis.google.com/chart?chst=d_map_pin_letter&chld=108|FF0000|000000"}},
{"geometry":{"coordinates":[106.587438333333,10.88312],"type":"Point"},"id":109,"type":"Feature","properties":{"date":"2016-09-17 14:14:10","icon":"http://chart.apis.google.com/chart?chst=d_map_pin_letter&chld=109|FF0000|000000"}},
{"geometry":{"coordinates":[106.588403333333,10.8817483333333],"type":"Point"},"id":110,"type":"Feature","properties":{"date":"2016-09-17 14:14:30","icon":"http://chart.apis.google.com/chart?chst=d_map_pin_letter&chld=110|FF0000|000000"}},
{"geometry":{"coordinates":[106.58998,10.8795016666667],"type":"Point"},"id":111,"type":"Feature","properties":{"date":"2016-09-17 14:14:50","icon":"http://chart.apis.google.com/chart?chst=d_map_pin_letter&chld=111|FF0000|000000"}},
{"geometry":{"coordinates":[106.590975,10.8780816666667],"type":"Point"},"id":112,"type":"Feature","properties":{"date":"2016-09-17 14:15:10","icon":"http://chart.apis.google.com/chart?chst=d_map_pin_letter&chld=112|FF0000|000000"}},
{"geometry":{"coordinates":[106.591988333333,10.876735],"type":"Point"},"id":113,"type":"Feature","properties":{"date":"2016-09-17 14:15:30","icon":"http://chart.apis.google.com/chart?chst=d_map_pin_letter&chld=113|FF0000|000000"}},
{"geometry":{"coordinates":[106.593676666667,10.8743683333333],"type":"Point"},"id":114,"type":"Feature","properties":{"date":"2016-09-17 14:15:50","icon":"http://chart.apis.google.com/chart?chst=d_map_pin_letter&chld=114|FF0000|000000"}},
{"geometry":{"coordinates":[106.595176666667,10.872175],"type":"Point"},"id":115,"type":"Feature","properties":{"date":"2016-09-17 14:16:10","icon":"http://chart.apis.google.com/chart?chst=d_map_pin_letter&chld=115|FF0000|000000"}},
{"geometry":{"coordinates":[106.596113333333,10.87081],"type":"Point"},"id":116,"type":"Feature","properties":{"date":"2016-09-17 14:16:30","icon":"http://chart.apis.google.com/chart?chst=d_map_pin_letter&chld=116|FF0000|000000"}},
{"geometry":{"coordinates":[106.596291666667,10.87056],"type":"Point"},"id":117,"type":"Feature","properties":{"date":"2016-09-17 14:16:39","icon":"http://chart.apis.google.com/chart?chst=d_map_pin_letter&chld=117|FF0000|000000"}},
{"geometry":{"coordinates":[106.596403333333,10.8704283333333],"type":"Point"},"id":118,"type":"Feature","properties":{"date":"2016-09-17 14:16:53","icon":"http://chart.apis.google.com/chart?chst=d_map_pin_letter&chld=118|FF0000|000000"}},
{"geometry":{"coordinates":[106.597426666667,10.8690683333333],"type":"Point"},"id":119,"type":"Feature","properties":{"date":"2016-09-17 14:17:13","icon":"http://chart.apis.google.com/chart?chst=d_map_pin_letter&chld=119|FF0000|000000"}},
{"geometry":{"coordinates":[106.598746666667,10.8672133333333],"type":"Point"},"id":120,"type":"Feature","properties":{"date":"2016-09-17 14:17:33","icon":"http://chart.apis.google.com/chart?chst=d_map_pin_letter&chld=120|FF0000|000000"}},
{"geometry":{"coordinates":[106.600106666667,10.8653],"type":"Point"},"id":121,"type":"Feature","properties":{"date":"2016-09-17 14:17:53","icon":"http://chart.apis.google.com/chart?chst=d_map_pin_letter&chld=121|FF0000|000000"}},
{"geometry":{"coordinates":[106.60135,10.86354],"type":"Point"},"id":122,"type":"Feature","properties":{"date":"2016-09-17 14:18:13","icon":"http://chart.apis.google.com/chart?chst=d_map_pin_letter&chld=122|FF0000|000000"}},
{"geometry":{"coordinates":[106.602333333333,10.8620716666667],"type":"Point"},"id":123,"type":"Feature","properties":{"date":"2016-09-17 14:18:33","icon":"http://chart.apis.google.com/chart?chst=d_map_pin_letter&chld=123|FF0000|000000"}},
{"geometry":{"coordinates":[106.602663333333,10.8616],"type":"Point"},"id":124,"type":"Feature","properties":{"date":"2016-09-17 14:18:53","icon":"http://chart.apis.google.com/chart?chst=d_map_pin_letter&chld=124|FF0000|000000"}},
{"geometry":{"coordinates":[106.60345,10.8605066666667],"type":"Point"},"id":125,"type":"Feature","properties":{"date":"2016-09-17 14:19:13","icon":"http://chart.apis.google.com/chart?chst=d_map_pin_letter&chld=125|FF0000|000000"}},
{"geometry":{"coordinates":[106.604511666667,10.85902],"type":"Point"},"id":126,"type":"Feature","properties":{"date":"2016-09-17 14:19:33","icon":"http://chart.apis.google.com/chart?chst=d_map_pin_letter&chld=126|FF0000|000000"}},
{"geometry":{"coordinates":[106.60561,10.85746],"type":"Point"},"id":127,"type":"Feature","properties":{"date":"2016-09-17 14:19:53","icon":"http://chart.apis.google.com/chart?chst=d_map_pin_letter&chld=127|FF0000|000000"}},
{"geometry":{"coordinates":[106.606191666667,10.856605],"type":"Point"},"id":128,"type":"Feature","properties":{"date":"2016-09-17 14:20:09","icon":"http://chart.apis.google.com/chart?chst=d_map_pin_letter&chld=128|FF0000|000000"}},
{"geometry":{"coordinates":[106.606248333333,10.8565216666667],"type":"Point"},"id":129,"type":"Feature","properties":{"date":"2016-09-17 14:20:14","icon":"http://chart.apis.google.com/chart?chst=d_map_pin_letter&chld=129|FF0000|000000"}},
{"geometry":{"coordinates":[106.606801666667,10.8556733333333],"type":"Point"},"id":130,"type":"Feature","properties":{"date":"2016-09-17 14:20:34","icon":"http://chart.apis.google.com/chart?chst=d_map_pin_letter&chld=130|FF0000|000000"}},
{"geometry":{"coordinates":[106.607451666667,10.8547583333333],"type":"Point"},"id":131,"type":"Feature","properties":{"date":"2016-09-17 14:20:54","icon":"http://chart.apis.google.com/chart?chst=d_map_pin_letter&chld=131|FF0000|000000"}},
{"geometry":{"coordinates":[106.608536666667,10.8531016666667],"type":"Point"},"id":132,"type":"Feature","properties":{"date":"2016-09-17 14:21:14","icon":"http://chart.apis.google.com/chart?chst=d_map_pin_letter&chld=132|FF0000|000000"}},
{"geometry":{"coordinates":[106.609645,10.8513783333333],"type":"Point"},"id":133,"type":"Feature","properties":{"date":"2016-09-17 14:21:34","icon":"http://chart.apis.google.com/chart?chst=d_map_pin_letter&chld=133|FF0000|000000"}},
{"geometry":{"coordinates":[106.610711666667,10.849705],"type":"Point"},"id":134,"type":"Feature","properties":{"date":"2016-09-17 14:21:54","icon":"http://chart.apis.google.com/chart?chst=d_map_pin_letter&chld=134|FF0000|000000"}},
{"geometry":{"coordinates":[106.611803333333,10.848025],"type":"Point"},"id":135,"type":"Feature","properties":{"date":"2016-09-17 14:22:14","icon":"http://chart.apis.google.com/chart?chst=d_map_pin_letter&chld=135|FF0000|000000"}},
{"geometry":{"coordinates":[106.612551666667,10.8467833333333],"type":"Point"},"id":136,"type":"Feature","properties":{"date":"2016-09-17 14:22:34","icon":"http://chart.apis.google.com/chart?chst=d_map_pin_letter&chld=136|FF0000|000000"}},
{"geometry":{"coordinates":[106.613203333333,10.8457666666667],"type":"Point"},"id":137,"type":"Feature","properties":{"date":"2016-09-17 14:22:54","icon":"http://chart.apis.google.com/chart?chst=d_map_pin_letter&chld=137|FF0000|000000"}},
{"geometry":{"coordinates":[106.61364,10.8450533333333],"type":"Point"},"id":138,"type":"Feature","properties":{"date":"2016-09-17 14:23:08","icon":"http://chart.apis.google.com/chart?chst=d_map_pin_letter&chld=138|FF0000|000000"}},
{"geometry":{"coordinates":[106.613726666667,10.8449033333333],"type":"Point"},"id":139,"type":"Feature","properties":{"date":"2016-09-17 14:23:26","icon":"http://chart.apis.google.com/chart?chst=d_map_pin_letter&chld=139|FF0000|000000"}},
{"geometry":{"coordinates":[106.613951666667,10.844595],"type":"Point"},"id":140,"type":"Feature","properties":{"date":"2016-09-17 14:23:33","icon":"http://chart.apis.google.com/chart?chst=d_map_pin_letter&chld=140|FF0000|000000"}},
{"geometry":{"coordinates":[106.61398,10.8445466666667],"type":"Point"},"id":141,"type":"Feature","properties":{"date":"2016-09-17 14:23:34","icon":"http://chart.apis.google.com/chart?chst=d_map_pin_letter&chld=141|FF0000|000000"}},
{"geometry":{"coordinates":[106.613806666667,10.8442483333333],"type":"Point"},"id":142,"type":"Feature","properties":{"date":"2016-09-17 14:23:54","icon":"http://chart.apis.google.com/chart?chst=d_map_pin_letter&chld=142|FF0000|000000"}}
]}