{
 "type": "FeatureCollection",
"features": [
{"geometry":{"coordinates":[106.614033333333,10.8444083333333],"type":"Point"},"id":0,"type":"Feature","properties":{"date":"2016-10-21 05:55:26","icon":"http://chart.apis.google.com/chart?chst=d_map_pin_letter&chld=0|FF0000|000000"}},
{"geometry":{"coordinates":[106.613986666667,10.8445583333333],"type":"Point"},"id":1,"type":"Feature","properties":{"date":"2016-10-21 05:55:41","icon":"http://chart.apis.google.com/chart?chst=d_map_pin_letter&chld=1|FF0000|000000"}},
{"geometry":{"coordinates":[106.613838333333,10.8447733333333],"type":"Point"},"id":2,"type":"Feature","properties":{"date":"2016-10-21 05:56:01","icon":"http://chart.apis.google.com/chart?chst=d_map_pin_letter&chld=2|FF0000|000000"}},
{"geometry":{"coordinates":[106.613838333333,10.8447733333333],"type":"Point"},"id":3,"type":"Feature","properties":{"date":"2016-10-21 05:56:21","icon":"http://chart.apis.google.com/chart?chst=d_map_pin_letter&chld=3|FF0000|000000"}},
{"geometry":{"coordinates":[106.613838333333,10.8447733333333],"type":"Point"},"id":4,"type":"Feature","properties":{"date":"2016-10-21 05:56:41","icon":"http://chart.apis.google.com/chart?chst=d_map_pin_letter&chld=4|FF0000|000000"}},
{"geometry":{"coordinates":[106.613838333333,10.8447733333333],"type":"Point"},"id":5,"type":"Feature","properties":{"date":"2016-10-21 05:57:01","icon":"http://chart.apis.google.com/chart?chst=d_map_pin_letter&chld=5|FF0000|000000"}},
{"geometry":{"coordinates":[106.612436666667,10.8468583333333],"type":"Point"},"id":6,"type":"Feature","properties":{"date":"2016-10-21 05:58:16","icon":"http://chart.apis.google.com/chart?chst=d_map_pin_letter&chld=6|FF0000|000000"}},
{"geometry":{"coordinates":[106.611606666667,10.848115],"type":"Point"},"id":7,"type":"Feature","properties":{"date":"2016-10-21 05:58:36","icon":"http://chart.apis.google.com/chart?chst=d_map_pin_letter&chld=7|FF0000|000000"}},
{"geometry":{"coordinates":[106.61073,10.8494266666667],"type":"Point"},"id":8,"type":"Feature","properties":{"date":"2016-10-21 05:58:56","icon":"http://chart.apis.google.com/chart?chst=d_map_pin_letter&chld=8|FF0000|000000"}},
{"geometry":{"coordinates":[106.609856666667,10.850875],"type":"Point"},"id":9,"type":"Feature","properties":{"date":"2016-10-21 05:59:16","icon":"http://chart.apis.google.com/chart?chst=d_map_pin_letter&chld=9|FF0000|000000"}},
{"geometry":{"coordinates":[106.608981666667,10.852285],"type":"Point"},"id":10,"type":"Feature","properties":{"date":"2016-10-21 05:59:36","icon":"http://chart.apis.google.com/chart?chst=d_map_pin_letter&chld=10|FF0000|000000"}},
{"geometry":{"coordinates":[106.608226666667,10.8536516666667],"type":"Point"},"id":11,"type":"Feature","properties":{"date":"2016-10-21 05:59:56","icon":"http://chart.apis.google.com/chart?chst=d_map_pin_letter&chld=11|FF0000|000000"}},
{"geometry":{"coordinates":[106.60755,10.8547283333333],"type":"Point"},"id":12,"type":"Feature","properties":{"date":"2016-10-21 06:00:16","icon":"http://chart.apis.google.com/chart?chst=d_map_pin_letter&chld=12|FF0000|000000"}},
{"geometry":{"coordinates":[106.607351666667,10.8550366666667],"type":"Point"},"id":13,"type":"Feature","properties":{"date":"2016-10-21 06:00:56","icon":"http://chart.apis.google.com/chart?chst=d_map_pin_letter&chld=13|FF0000|000000"}},
{"geometry":{"coordinates":[106.607351666667,10.8550366666667],"type":"Point"},"id":14,"type":"Feature","properties":{"date":"2016-10-21 06:01:16","icon":"http://chart.apis.google.com/chart?chst=d_map_pin_letter&chld=14|FF0000|000000"}},
{"geometry":{"coordinates":[106.60731,10.8551916666667],"type":"Point"},"id":15,"type":"Feature","properties":{"date":"2016-10-21 06:01:24","icon":"http://chart.apis.google.com/chart?chst=d_map_pin_letter&chld=15|FF0000|000000"}},
{"geometry":{"coordinates":[106.606701666667,10.8562433333333],"type":"Point"},"id":16,"type":"Feature","properties":{"date":"2016-10-21 06:01:44","icon":"http://chart.apis.google.com/chart?chst=d_map_pin_letter&chld=16|FF0000|000000"}},
{"geometry":{"coordinates":[106.60557,10.857985],"type":"Point"},"id":17,"type":"Feature","properties":{"date":"2016-10-21 06:02:04","icon":"http://chart.apis.google.com/chart?chst=d_map_pin_letter&chld=17|FF0000|000000"}},
{"geometry":{"coordinates":[106.604395,10.859605],"type":"Point"},"id":18,"type":"Feature","properties":{"date":"2016-10-21 06:02:24","icon":"http://chart.apis.google.com/chart?chst=d_map_pin_letter&chld=18|FF0000|000000"}},
{"geometry":{"coordinates":[106.60335,10.86102],"type":"Point"},"id":19,"type":"Feature","properties":{"date":"2016-10-21 06:02:44","icon":"http://chart.apis.google.com/chart?chst=d_map_pin_letter&chld=19|FF0000|000000"}},
{"geometry":{"coordinates":[106.602861666667,10.86163],"type":"Point"},"id":20,"type":"Feature","properties":{"date":"2016-10-21 06:02:56","icon":"http://chart.apis.google.com/chart?chst=d_map_pin_letter&chld=20|FF0000|000000"}},
{"geometry":{"coordinates":[106.602543333333,10.8621433333333],"type":"Point"},"id":21,"type":"Feature","properties":{"date":"2016-10-21 06:03:16","icon":"http://chart.apis.google.com/chart?chst=d_map_pin_letter&chld=21|FF0000|000000"}},
{"geometry":{"coordinates":[106.601951666667,10.8629016666667],"type":"Point"},"id":22,"type":"Feature","properties":{"date":"2016-10-21 06:03:36","icon":"http://chart.apis.google.com/chart?chst=d_map_pin_letter&chld=22|FF0000|000000"}},
{"geometry":{"coordinates":[106.601171666667,10.864175],"type":"Point"},"id":23,"type":"Feature","properties":{"date":"2016-10-21 06:03:56","icon":"http://chart.apis.google.com/chart?chst=d_map_pin_letter&chld=23|FF0000|000000"}},
{"geometry":{"coordinates":[106.600136666667,10.86572],"type":"Point"},"id":24,"type":"Feature","properties":{"date":"2016-10-21 06:04:16","icon":"http://chart.apis.google.com/chart?chst=d_map_pin_letter&chld=24|FF0000|000000"}},
{"geometry":{"coordinates":[106.599196666667,10.8671616666667],"type":"Point"},"id":25,"type":"Feature","properties":{"date":"2016-10-21 06:04:36","icon":"http://chart.apis.google.com/chart?chst=d_map_pin_letter&chld=25|FF0000|000000"}},
{"geometry":{"coordinates":[106.598635,10.8678616666667],"type":"Point"},"id":26,"type":"Feature","properties":{"date":"2016-10-21 06:04:56","icon":"http://chart.apis.google.com/chart?chst=d_map_pin_letter&chld=26|FF0000|000000"}},
{"geometry":{"coordinates":[106.597616666667,10.869305],"type":"Point"},"id":27,"type":"Feature","properties":{"date":"2016-10-21 06:05:16","icon":"http://chart.apis.google.com/chart?chst=d_map_pin_letter&chld=27|FF0000|000000"}},
{"geometry":{"coordinates":[106.597063333333,10.87011],"type":"Point"},"id":28,"type":"Feature","properties":{"date":"2016-10-21 06:05:35","icon":"http://chart.apis.google.com/chart?chst=d_map_pin_letter&chld=28|FF0000|000000"}},
{"geometry":{"coordinates":[106.596906666667,10.8702916666667],"type":"Point"},"id":29,"type":"Feature","properties":{"date":"2016-10-21 06:05:54","icon":"http://chart.apis.google.com/chart?chst=d_map_pin_letter&chld=29|FF0000|000000"}},
{"geometry":{"coordinates":[106.59616,10.8713616666667],"type":"Point"},"id":30,"type":"Feature","properties":{"date":"2016-10-21 06:06:14","icon":"http://chart.apis.google.com/chart?chst=d_map_pin_letter&chld=30|FF0000|000000"}},
{"geometry":{"coordinates":[106.595015,10.8730333333333],"type":"Point"},"id":31,"type":"Feature","properties":{"date":"2016-10-21 06:06:34","icon":"http://chart.apis.google.com/chart?chst=d_map_pin_letter&chld=31|FF0000|000000"}},
{"geometry":{"coordinates":[106.593881666667,10.8747833333333],"type":"Point"},"id":32,"type":"Feature","properties":{"date":"2016-10-21 06:06:54","icon":"http://chart.apis.google.com/chart?chst=d_map_pin_letter&chld=32|FF0000|000000"}},
{"geometry":{"coordinates":[106.59284,10.8761683333333],"type":"Point"},"id":33,"type":"Feature","properties":{"date":"2016-10-21 06:07:14","icon":"http://chart.apis.google.com/chart?chst=d_map_pin_letter&chld=33|FF0000|000000"}},
{"geometry":{"coordinates":[106.59195,10.8775366666667],"type":"Point"},"id":34,"type":"Feature","properties":{"date":"2016-10-21 06:07:34","icon":"http://chart.apis.google.com/chart?chst=d_map_pin_letter&chld=34|FF0000|000000"}},
{"geometry":{"coordinates":[106.591833333333,10.8777716666667],"type":"Point"},"id":35,"type":"Feature","properties":{"date":"2016-10-21 06:07:40","icon":"http://chart.apis.google.com/chart?chst=d_map_pin_letter&chld=35|FF0000|000000"}},
{"geometry":{"coordinates":[106.591785,10.877825],"type":"Point"},"id":36,"type":"Feature","properties":{"date":"2016-10-21 06:07:47","icon":"http://chart.apis.google.com/chart?chst=d_map_pin_letter&chld=36|FF0000|000000"}},
{"geometry":{"coordinates":[106.591785,10.877825],"type":"Point"},"id":37,"type":"Feature","properties":{"date":"2016-10-21 06:08:07","icon":"http://chart.apis.google.com/chart?chst=d_map_pin_letter&chld=37|FF0000|000000"}},
{"geometry":{"coordinates":[106.591785,10.877825],"type":"Point"},"id":38,"type":"Feature","properties":{"date":"2016-10-21 06:08:27","icon":"http://chart.apis.google.com/chart?chst=d_map_pin_letter&chld=38|FF0000|000000"}},
{"geometry":{"coordinates":[106.591695,10.877935],"type":"Point"},"id":39,"type":"Feature","properties":{"date":"2016-10-21 06:08:29","icon":"http://chart.apis.google.com/chart?chst=d_map_pin_letter&chld=39|FF0000|000000"}},
{"geometry":{"coordinates":[106.590728333333,10.8791333333333],"type":"Point"},"id":40,"type":"Feature","properties":{"date":"2016-10-21 06:08:49","icon":"http://chart.apis.google.com/chart?chst=d_map_pin_letter&chld=40|FF0000|000000"}},
{"geometry":{"coordinates":[106.589503333333,10.8808583333333],"type":"Point"},"id":41,"type":"Feature","properties":{"date":"2016-10-21 06:09:09","icon":"http://chart.apis.google.com/chart?chst=d_map_pin_letter&chld=41|FF0000|000000"}},
{"geometry":{"coordinates":[106.588328333333,10.882495],"type":"Point"},"id":42,"type":"Feature","properties":{"date":"2016-10-21 06:09:29","icon":"http://chart.apis.google.com/chart?chst=d_map_pin_letter&chld=42|FF0000|000000"}},
{"geometry":{"coordinates":[106.587508333333,10.8836883333333],"type":"Point"},"id":43,"type":"Feature","properties":{"date":"2016-10-21 06:09:49","icon":"http://chart.apis.google.com/chart?chst=d_map_pin_letter&chld=43|FF0000|000000"}},
{"geometry":{"coordinates":[106.587448333333,10.8837366666667],"type":"Point"},"id":44,"type":"Feature","properties":{"date":"2016-10-21 06:09:55","icon":"http://chart.apis.google.com/chart?chst=d_map_pin_letter&chld=44|FF0000|000000"}},
{"geometry":{"coordinates":[106.587448333333,10.8837366666667],"type":"Point"},"id":45,"type":"Feature","properties":{"date":"2016-10-21 06:10:15","icon":"http://chart.apis.google.com/chart?chst=d_map_pin_letter&chld=45|FF0000|000000"}},
{"geometry":{"coordinates":[106.58735,10.8838166666667],"type":"Point"},"id":46,"type":"Feature","properties":{"date":"2016-10-21 06:10:27","icon":"http://chart.apis.google.com/chart?chst=d_map_pin_letter&chld=46|FF0000|000000"}},
{"geometry":{"coordinates":[106.586833333333,10.884595],"type":"Point"},"id":47,"type":"Feature","properties":{"date":"2016-10-21 06:10:48","icon":"http://chart.apis.google.com/chart?chst=d_map_pin_letter&chld=47|FF0000|000000"}},
{"geometry":{"coordinates":[106.58636,10.8851566666667],"type":"Point"},"id":48,"type":"Feature","properties":{"date":"2016-10-21 06:11:07","icon":"http://chart.apis.google.com/chart?chst=d_map_pin_letter&chld=48|FF0000|000000"}},
{"geometry":{"coordinates":[106.585141666667,10.8868116666667],"type":"Point"},"id":49,"type":"Feature","properties":{"date":"2016-10-21 06:11:27","icon":"http://chart.apis.google.com/chart?chst=d_map_pin_letter&chld=49|FF0000|000000"}},
{"geometry":{"coordinates":[106.583881666667,10.888755],"type":"Point"},"id":50,"type":"Feature","properties":{"date":"2016-10-21 06:11:48","icon":"http://chart.apis.google.com/chart?chst=d_map_pin_letter&chld=50|FF0000|000000"}},
{"geometry":{"coordinates":[106.583825,10.8888333333333],"type":"Point"},"id":51,"type":"Feature","properties":{"date":"2016-10-21 06:11:55","icon":"http://chart.apis.google.com/chart?chst=d_map_pin_letter&chld=51|FF0000|000000"}},
{"geometry":{"coordinates":[106.583748333333,10.888935],"type":"Point"},"id":52,"type":"Feature","properties":{"date":"2016-10-21 06:11:58","icon":"http://chart.apis.google.com/chart?chst=d_map_pin_letter&chld=52|FF0000|000000"}},
{"geometry":{"coordinates":[106.58287,10.8902016666667],"type":"Point"},"id":53,"type":"Feature","properties":{"date":"2016-10-21 06:12:18","icon":"http://chart.apis.google.com/chart?chst=d_map_pin_letter&chld=53|FF0000|000000"}},
{"geometry":{"coordinates":[106.581703333333,10.8919733333333],"type":"Point"},"id":54,"type":"Feature","properties":{"date":"2016-10-21 06:12:39","icon":"http://chart.apis.google.com/chart?chst=d_map_pin_letter&chld=54|FF0000|000000"}},
{"geometry":{"coordinates":[106.58136,10.8924583333333],"type":"Point"},"id":55,"type":"Feature","properties":{"date":"2016-10-21 06:12:54","icon":"http://chart.apis.google.com/chart?chst=d_map_pin_letter&chld=55|FF0000|000000"}},
{"geometry":{"coordinates":[106.58136,10.8924583333333],"type":"Point"},"id":56,"type":"Feature","properties":{"date":"2016-10-21 06:13:13","icon":"http://chart.apis.google.com/chart?chst=d_map_pin_letter&chld=56|FF0000|000000"}},
{"geometry":{"coordinates":[106.581195,10.8925583333333],"type":"Point"},"id":57,"type":"Feature","properties":{"date":"2016-10-21 06:13:29","icon":"http://chart.apis.google.com/chart?chst=d_map_pin_letter&chld=57|FF0000|000000"}},
{"geometry":{"coordinates":[106.580371666667,10.89385],"type":"Point"},"id":58,"type":"Feature","properties":{"date":"2016-10-21 06:13:48","icon":"http://chart.apis.google.com/chart?chst=d_map_pin_letter&chld=58|FF0000|000000"}},
{"geometry":{"coordinates":[106.578911666667,10.8959383333333],"type":"Point"},"id":59,"type":"Feature","properties":{"date":"2016-10-21 06:14:08","icon":"http://chart.apis.google.com/chart?chst=d_map_pin_letter&chld=59|FF0000|000000"}},
{"geometry":{"coordinates":[106.577431666667,10.8979866666667],"type":"Point"},"id":60,"type":"Feature","properties":{"date":"2016-10-21 06:14:29","icon":"http://chart.apis.google.com/chart?chst=d_map_pin_letter&chld=60|FF0000|000000"}},
{"geometry":{"coordinates":[106.57611,10.8998716666667],"type":"Point"},"id":61,"type":"Feature","properties":{"date":"2016-10-21 06:14:49","icon":"http://chart.apis.google.com/chart?chst=d_map_pin_letter&chld=61|FF0000|000000"}},
{"geometry":{"coordinates":[106.57487,10.9016333333333],"type":"Point"},"id":62,"type":"Feature","properties":{"date":"2016-10-21 06:15:09","icon":"http://chart.apis.google.com/chart?chst=d_map_pin_letter&chld=62|FF0000|000000"}},
{"geometry":{"coordinates":[106.573321666667,10.9037583333333],"type":"Point"},"id":63,"type":"Feature","properties":{"date":"2016-10-21 06:15:29","icon":"http://chart.apis.google.com/chart?chst=d_map_pin_letter&chld=63|FF0000|000000"}},
{"geometry":{"coordinates":[106.571771666667,10.9058366666667],"type":"Point"},"id":64,"type":"Feature","properties":{"date":"2016-10-21 06:15:49","icon":"http://chart.apis.google.com/chart?chst=d_map_pin_letter&chld=64|FF0000|000000"}},
{"geometry":{"coordinates":[106.57025,10.9080266666667],"type":"Point"},"id":65,"type":"Feature","properties":{"date":"2016-10-21 06:16:09","icon":"http://chart.apis.google.com/chart?chst=d_map_pin_letter&chld=65|FF0000|000000"}},
{"geometry":{"coordinates":[106.568716666667,10.9101133333333],"type":"Point"},"id":66,"type":"Feature","properties":{"date":"2016-10-21 06:16:29","icon":"http://chart.apis.google.com/chart?chst=d_map_pin_letter&chld=66|FF0000|000000"}},
{"geometry":{"coordinates":[106.567368333333,10.9120266666667],"type":"Point"},"id":67,"type":"Feature","properties":{"date":"2016-10-21 06:16:49","icon":"http://chart.apis.google.com/chart?chst=d_map_pin_letter&chld=67|FF0000|000000"}},
{"geometry":{"coordinates":[106.565908333333,10.914175],"type":"Point"},"id":68,"type":"Feature","properties":{"date":"2016-10-21 06:17:09","icon":"http://chart.apis.google.com/chart?chst=d_map_pin_letter&chld=68|FF0000|000000"}},
{"geometry":{"coordinates":[106.564356666667,10.9164266666667],"type":"Point"},"id":69,"type":"Feature","properties":{"date":"2016-10-21 06:17:29","icon":"http://chart.apis.google.com/chart?chst=d_map_pin_letter&chld=69|FF0000|000000"}},
{"geometry":{"coordinates":[106.563845,10.9172316666667],"type":"Point"},"id":70,"type":"Feature","properties":{"date":"2016-10-21 06:17:49","icon":"http://chart.apis.google.com/chart?chst=d_map_pin_letter&chld=70|FF0000|000000"}},
{"geometry":{"coordinates":[106.562633333333,10.9189683333333],"type":"Point"},"id":71,"type":"Feature","properties":{"date":"2016-10-21 06:18:09","icon":"http://chart.apis.google.com/chart?chst=d_map_pin_letter&chld=71|FF0000|000000"}},
{"geometry":{"coordinates":[106.560841666667,10.9215366666667],"type":"Point"},"id":72,"type":"Feature","properties":{"date":"2016-10-21 06:18:29","icon":"http://chart.apis.google.com/chart?chst=d_map_pin_letter&chld=72|FF0000|000000"}},
{"geometry":{"coordinates":[106.559023333333,10.9241416666667],"type":"Point"},"id":73,"type":"Feature","properties":{"date":"2016-10-21 06:18:49","icon":"http://chart.apis.google.com/chart?chst=d_map_pin_letter&chld=73|FF0000|000000"}},
{"geometry":{"coordinates":[106.557518333333,10.9263366666667],"type":"Point"},"id":74,"type":"Feature","properties":{"date":"2016-10-21 06:19:09","icon":"http://chart.apis.google.com/chart?chst=d_map_pin_letter&chld=74|FF0000|000000"}},
{"geometry":{"coordinates":[106.556703333333,10.9275616666667],"type":"Point"},"id":75,"type":"Feature","properties":{"date":"2016-10-21 06:19:29","icon":"http://chart.apis.google.com/chart?chst=d_map_pin_letter&chld=75|FF0000|000000"}},
{"geometry":{"coordinates":[106.556703333333,10.9275616666667],"type":"Point"},"id":76,"type":"Feature","properties":{"date":"2016-10-21 06:19:31","icon":"http://chart.apis.google.com/chart?chst=d_map_pin_letter&chld=76|FF0000|000000"}},
{"geometry":{"coordinates":[106.55668,10.9276033333333],"type":"Point"},"id":77,"type":"Feature","properties":{"date":"2016-10-21 06:19:38","icon":"http://chart.apis.google.com/chart?chst=d_map_pin_letter&chld=77|FF0000|000000"}},
{"geometry":{"coordinates":[106.555585,10.9290166666667],"type":"Point"},"id":78,"type":"Feature","properties":{"date":"2016-10-21 06:19:58","icon":"http://chart.apis.google.com/chart?chst=d_map_pin_letter&chld=78|FF0000|000000"}},
{"geometry":{"coordinates":[106.553858333333,10.9310933333333],"type":"Point"},"id":79,"type":"Feature","properties":{"date":"2016-10-21 06:20:18","icon":"http://chart.apis.google.com/chart?chst=d_map_pin_letter&chld=79|FF0000|000000"}},
{"geometry":{"coordinates":[106.553691666667,10.9313],"type":"Point"},"id":80,"type":"Feature","properties":{"date":"2016-10-21 06:20:26","icon":"http://chart.apis.google.com/chart?chst=d_map_pin_letter&chld=80|FF0000|000000"}},
{"geometry":{"coordinates":[106.553591666667,10.9313616666667],"type":"Point"},"id":81,"type":"Feature","properties":{"date":"2016-10-21 06:20:36","icon":"http://chart.apis.google.com/chart?chst=d_map_pin_letter&chld=81|FF0000|000000"}},
{"geometry":{"coordinates":[106.55258,10.9324766666667],"type":"Point"},"id":82,"type":"Feature","properties":{"date":"2016-10-21 06:20:56","icon":"http://chart.apis.google.com/chart?chst=d_map_pin_letter&chld=82|FF0000|000000"}},
{"geometry":{"coordinates":[106.550645,10.93434],"type":"Point"},"id":83,"type":"Feature","properties":{"date":"2016-10-21 06:21:16","icon":"http://chart.apis.google.com/chart?chst=d_map_pin_letter&chld=83|FF0000|000000"}},
{"geometry":{"coordinates":[106.550058333333,10.934725],"type":"Point"},"id":84,"type":"Feature","properties":{"date":"2016-10-21 06:21:30","icon":"http://chart.apis.google.com/chart?chst=d_map_pin_letter&chld=84|FF0000|000000"}},
{"geometry":{"coordinates":[106.550058333333,10.934725],"type":"Point"},"id":85,"type":"Feature","properties":{"date":"2016-10-21 06:21:50","icon":"http://chart.apis.google.com/chart?chst=d_map_pin_letter&chld=85|FF0000|000000"}},
{"geometry":{"coordinates":[106.549971666667,10.9347883333333],"type":"Point"},"id":86,"type":"Feature","properties":{"date":"2016-10-21 06:22:00","icon":"http://chart.apis.google.com/chart?chst=d_map_pin_letter&chld=86|FF0000|000000"}},
{"geometry":{"coordinates":[106.549478333333,10.93503],"type":"Point"},"id":87,"type":"Feature","properties":{"date":"2016-10-21 06:22:14","icon":"http://chart.apis.google.com/chart?chst=d_map_pin_letter&chld=87|FF0000|000000"}},
{"geometry":{"coordinates":[106.54938,10.9350616666667],"type":"Point"},"id":88,"type":"Feature","properties":{"date":"2016-10-21 06:22:19","icon":"http://chart.apis.google.com/chart?chst=d_map_pin_letter&chld=88|FF0000|000000"}},
{"geometry":{"coordinates":[106.547546666667,10.93592],"type":"Point"},"id":89,"type":"Feature","properties":{"date":"2016-10-21 06:22:39","icon":"http://chart.apis.google.com/chart?chst=d_map_pin_letter&chld=89|FF0000|000000"}},
{"geometry":{"coordinates":[106.54489,10.9371633333333],"type":"Point"},"id":90,"type":"Feature","properties":{"date":"2016-10-21 06:22:59","icon":"http://chart.apis.google.com/chart?chst=d_map_pin_letter&chld=90|FF0000|000000"}},
{"geometry":{"coordinates":[106.543296666667,10.9379433333333],"type":"Point"},"id":91,"type":"Feature","properties":{"date":"2016-10-21 06:23:16","icon":"http://chart.apis.google.com/chart?chst=d_map_pin_letter&chld=91|FF0000|000000"}},
{"geometry":{"coordinates":[106.543213333333,10.9379666666667],"type":"Point"},"id":92,"type":"Feature","properties":{"date":"2016-10-21 06:23:29","icon":"http://chart.apis.google.com/chart?chst=d_map_pin_letter&chld=92|FF0000|000000"}},
{"geometry":{"coordinates":[106.541701666667,10.93867],"type":"Point"},"id":93,"type":"Feature","properties":{"date":"2016-10-21 06:23:49","icon":"http://chart.apis.google.com/chart?chst=d_map_pin_letter&chld=93|FF0000|000000"}},
{"geometry":{"coordinates":[106.541351666667,10.9388583333333],"type":"Point"},"id":94,"type":"Feature","properties":{"date":"2016-10-21 06:24:09","icon":"http://chart.apis.google.com/chart?chst=d_map_pin_letter&chld=94|FF0000|000000"}},
{"geometry":{"coordinates":[106.540171666667,10.9394433333333],"type":"Point"},"id":95,"type":"Feature","properties":{"date":"2016-10-21 06:24:27","icon":"http://chart.apis.google.com/chart?chst=d_map_pin_letter&chld=95|FF0000|000000"}},
{"geometry":{"coordinates":[106.539945,10.9395083333333],"type":"Point"},"id":96,"type":"Feature","properties":{"date":"2016-10-21 06:24:32","icon":"http://chart.apis.google.com/chart?chst=d_map_pin_letter&chld=96|FF0000|000000"}},
{"geometry":{"coordinates":[106.539905,10.9394983333333],"type":"Point"},"id":97,"type":"Feature","properties":{"date":"2016-10-21 06:24:44","icon":"http://chart.apis.google.com/chart?chst=d_map_pin_letter&chld=97|FF0000|000000"}},
{"geometry":{"coordinates":[106.539868333333,10.9395533333333],"type":"Point"},"id":98,"type":"Feature","properties":{"date":"2016-10-21 06:24:51","icon":"http://chart.apis.google.com/chart?chst=d_map_pin_letter&chld=98|FF0000|000000"}},
{"geometry":{"coordinates":[106.537958333333,10.9405083333333],"type":"Point"},"id":99,"type":"Feature","properties":{"date":"2016-10-21 06:25:11","icon":"http://chart.apis.google.com/chart?chst=d_map_pin_letter&chld=99|FF0000|000000"}},
{"geometry":{"coordinates":[106.536145,10.9413966666667],"type":"Point"},"id":100,"type":"Feature","properties":{"date":"2016-10-21 06:25:31","icon":"http://chart.apis.google.com/chart?chst=d_map_pin_letter&chld=100|FF0000|000000"}},
{"geometry":{"coordinates":[106.536075,10.94141],"type":"Point"},"id":101,"type":"Feature","properties":{"date":"2016-10-21 06:25:36","icon":"http://chart.apis.google.com/chart?chst=d_map_pin_letter&chld=101|FF0000|000000"}},
{"geometry":{"coordinates":[106.534153333333,10.942305],"type":"Point"},"id":102,"type":"Feature","properties":{"date":"2016-10-21 06:25:56","icon":"http://chart.apis.google.com/chart?chst=d_map_pin_letter&chld=102|FF0000|000000"}},
{"geometry":{"coordinates":[106.531283333333,10.943715],"type":"Point"},"id":103,"type":"Feature","properties":{"date":"2016-10-21 06:26:16","icon":"http://chart.apis.google.com/chart?chst=d_map_pin_letter&chld=103|FF0000|000000"}},
{"geometry":{"coordinates":[106.530821666667,10.9439516666667],"type":"Point"},"id":104,"type":"Feature","properties":{"date":"2016-10-21 06:26:26","icon":"http://chart.apis.google.com/chart?chst=d_map_pin_letter&chld=104|FF0000|000000"}},
{"geometry":{"coordinates":[106.530693333333,10.9440083333333],"type":"Point"},"id":105,"type":"Feature","properties":{"date":"2016-10-21 06:26:34","icon":"http://chart.apis.google.com/chart?chst=d_map_pin_letter&chld=105|FF0000|000000"}},
{"geometry":{"coordinates":[106.528571666667,10.94505],"type":"Point"},"id":106,"type":"Feature","properties":{"date":"2016-10-21 06:26:54","icon":"http://chart.apis.google.com/chart?chst=d_map_pin_letter&chld=106|FF0000|000000"}},
{"geometry":{"coordinates":[106.52534,10.9465933333333],"type":"Point"},"id":107,"type":"Feature","properties":{"date":"2016-10-21 06:27:14","icon":"http://chart.apis.google.com/chart?chst=d_map_pin_letter&chld=107|FF0000|000000"}},
{"geometry":{"coordinates":[106.524515,10.9470566666667],"type":"Point"},"id":108,"type":"Feature","properties":{"date":"2016-10-21 06:27:21","icon":"http://chart.apis.google.com/chart?chst=d_map_pin_letter&chld=108|FF0000|000000"}},
{"geometry":{"coordinates":[106.5244,10.9471233333333],"type":"Point"},"id":109,"type":"Feature","properties":{"date":"2016-10-21 06:27:29","icon":"http://chart.apis.google.com/chart?chst=d_map_pin_letter&chld=109|FF0000|000000"}},
{"geometry":{"coordinates":[106.524375,10.9471183333333],"type":"Point"},"id":110,"type":"Feature","properties":{"date":"2016-10-21 06:27:31","icon":"http://chart.apis.google.com/chart?chst=d_map_pin_letter&chld=110|FF0000|000000"}},
{"geometry":{"coordinates":[106.523816666667,10.9474866666667],"type":"Point"},"id":111,"type":"Feature","properties":{"date":"2016-10-21 06:27:49","icon":"http://chart.apis.google.com/chart?chst=d_map_pin_letter&chld=111|FF0000|000000"}},
{"geometry":{"coordinates":[106.52373,10.9475433333333],"type":"Point"},"id":112,"type":"Feature","properties":{"date":"2016-10-21 06:27:59","icon":"http://chart.apis.google.com/chart?chst=d_map_pin_letter&chld=112|FF0000|000000"}},
{"geometry":{"coordinates":[106.52196,10.9487383333333],"type":"Point"},"id":113,"type":"Feature","properties":{"date":"2016-10-21 06:28:19","icon":"http://chart.apis.google.com/chart?chst=d_map_pin_letter&chld=113|FF0000|000000"}},
{"geometry":{"coordinates":[106.519053333333,10.9506133333333],"type":"Point"},"id":114,"type":"Feature","properties":{"date":"2016-10-21 06:28:39","icon":"http://chart.apis.google.com/chart?chst=d_map_pin_letter&chld=114|FF0000|000000"}},
{"geometry":{"coordinates":[106.515776666667,10.952845],"type":"Point"},"id":115,"type":"Feature","properties":{"date":"2016-10-21 06:28:59","icon":"http://chart.apis.google.com/chart?chst=d_map_pin_letter&chld=115|FF0000|000000"}},
{"geometry":{"coordinates":[106.51387,10.9541816666667],"type":"Point"},"id":116,"type":"Feature","properties":{"date":"2016-10-21 06:29:11","icon":"http://chart.apis.google.com/chart?chst=d_map_pin_letter&chld=116|FF0000|000000"}},
{"geometry":{"coordinates":[106.513531666667,10.9544216666667],"type":"Point"},"id":117,"type":"Feature","properties":{"date":"2016-10-21 06:29:13","icon":"http://chart.apis.google.com/chart?chst=d_map_pin_letter&chld=117|FF0000|000000"}},
{"geometry":{"coordinates":[106.51303,10.954775],"type":"Point"},"id":118,"type":"Feature","properties":{"date":"2016-10-21 06:29:16","icon":"http://chart.apis.google.com/chart?chst=d_map_pin_letter&chld=118|FF0000|000000"}},
{"geometry":{"coordinates":[106.510018333333,10.95674],"type":"Point"},"id":119,"type":"Feature","properties":{"date":"2016-10-21 06:29:36","icon":"http://chart.apis.google.com/chart?chst=d_map_pin_letter&chld=119|FF0000|000000"}},
{"geometry":{"coordinates":[106.507206666667,10.9581933333333],"type":"Point"},"id":120,"type":"Feature","properties":{"date":"2016-10-21 06:29:56","icon":"http://chart.apis.google.com/chart?chst=d_map_pin_letter&chld=120|FF0000|000000"}},
{"geometry":{"coordinates":[106.505406666667,10.9591383333333],"type":"Point"},"id":121,"type":"Feature","properties":{"date":"2016-10-21 06:30:16","icon":"http://chart.apis.google.com/chart?chst=d_map_pin_letter&chld=121|FF0000|000000"}},
{"geometry":{"coordinates":[106.505338333333,10.9591516666667],"type":"Point"},"id":122,"type":"Feature","properties":{"date":"2016-10-21 06:30:20","icon":"http://chart.apis.google.com/chart?chst=d_map_pin_letter&chld=122|FF0000|000000"}},
{"geometry":{"coordinates":[106.50378,10.9600083333333],"type":"Point"},"id":123,"type":"Feature","properties":{"date":"2016-10-21 06:30:40","icon":"http://chart.apis.google.com/chart?chst=d_map_pin_letter&chld=123|FF0000|000000"}},
{"geometry":{"coordinates":[106.50154,10.9612433333333],"type":"Point"},"id":124,"type":"Feature","properties":{"date":"2016-10-21 06:31:00","icon":"http://chart.apis.google.com/chart?chst=d_map_pin_letter&chld=124|FF0000|000000"}},
{"geometry":{"coordinates":[106.501266666667,10.9613833333333],"type":"Point"},"id":125,"type":"Feature","properties":{"date":"2016-10-21 06:31:09","icon":"http://chart.apis.google.com/chart?chst=d_map_pin_letter&chld=125|FF0000|000000"}},
{"geometry":{"coordinates":[106.501216666667,10.9613966666667],"type":"Point"},"id":126,"type":"Feature","properties":{"date":"2016-10-21 06:31:11","icon":"http://chart.apis.google.com/chart?chst=d_map_pin_letter&chld=126|FF0000|000000"}},
{"geometry":{"coordinates":[106.499343333333,10.962465],"type":"Point"},"id":127,"type":"Feature","properties":{"date":"2016-10-21 06:31:32","icon":"http://chart.apis.google.com/chart?chst=d_map_pin_letter&chld=127|FF0000|000000"}},
{"geometry":{"coordinates":[106.4966,10.9640416666667],"type":"Point"},"id":128,"type":"Feature","properties":{"date":"2016-10-21 06:31:52","icon":"http://chart.apis.google.com/chart?chst=d_map_pin_letter&chld=128|FF0000|000000"}},
{"geometry":{"coordinates":[106.495901666667,10.9644],"type":"Point"},"id":129,"type":"Feature","properties":{"date":"2016-10-21 06:32:06","icon":"http://chart.apis.google.com/chart?chst=d_map_pin_letter&chld=129|FF0000|000000"}},
{"geometry":{"coordinates":[106.495795,10.964465],"type":"Point"},"id":130,"type":"Feature","properties":{"date":"2016-10-21 06:32:20","icon":"http://chart.apis.google.com/chart?chst=d_map_pin_letter&chld=130|FF0000|000000"}},
{"geometry":{"coordinates":[106.493856666667,10.9653283333333],"type":"Point"},"id":131,"type":"Feature","properties":{"date":"2016-10-21 06:32:40","icon":"http://chart.apis.google.com/chart?chst=d_map_pin_letter&chld=131|FF0000|000000"}},
{"geometry":{"coordinates":[106.490653333333,10.9666016666667],"type":"Point"},"id":132,"type":"Feature","properties":{"date":"2016-10-21 06:33:00","icon":"http://chart.apis.google.com/chart?chst=d_map_pin_letter&chld=132|FF0000|000000"}},
{"geometry":{"coordinates":[106.488463333333,10.96751],"type":"Point"},"id":133,"type":"Feature","properties":{"date":"2016-10-21 06:33:15","icon":"http://chart.apis.google.com/chart?chst=d_map_pin_letter&chld=133|FF0000|000000"}},
{"geometry":{"coordinates":[106.488163333333,10.9676416666667],"type":"Point"},"id":134,"type":"Feature","properties":{"date":"2016-10-21 06:33:25","icon":"http://chart.apis.google.com/chart?chst=d_map_pin_letter&chld=134|FF0000|000000"}},
{"geometry":{"coordinates":[106.488121666667,10.967625],"type":"Point"},"id":135,"type":"Feature","properties":{"date":"2016-10-21 06:33:32","icon":"http://chart.apis.google.com/chart?chst=d_map_pin_letter&chld=135|FF0000|000000"}},
{"geometry":{"coordinates":[106.486451666667,10.9681883333333],"type":"Point"},"id":136,"type":"Feature","properties":{"date":"2016-10-21 06:33:51","icon":"http://chart.apis.google.com/chart?chst=d_map_pin_letter&chld=136|FF0000|000000"}},
{"geometry":{"coordinates":[106.484088333333,10.9694916666667],"type":"Point"},"id":137,"type":"Feature","properties":{"date":"2016-10-21 06:34:12","icon":"http://chart.apis.google.com/chart?chst=d_map_pin_letter&chld=137|FF0000|000000"}},
{"geometry":{"coordinates":[106.482328333333,10.9706916666667],"type":"Point"},"id":138,"type":"Feature","properties":{"date":"2016-10-21 06:34:32","icon":"http://chart.apis.google.com/chart?chst=d_map_pin_letter&chld=138|FF0000|000000"}},
{"geometry":{"coordinates":[106.482001666667,10.9713233333333],"type":"Point"},"id":139,"type":"Feature","properties":{"date":"2016-10-21 06:34:52","icon":"http://chart.apis.google.com/chart?chst=d_map_pin_letter&chld=139|FF0000|000000"}}
]}