{
 "type": "FeatureCollection",
"features": [
{"geometry":{"coordinates":[106.614608333333,10.8436183333333],"type":"Point"},"id":0,"type":"Feature","properties":{"date":"2016-10-20 10:53:12","icon":"http://chart.apis.google.com/chart?chst=d_map_pin_letter&chld=0|FF0000|000000"}},
{"geometry":{"coordinates":[106.614921666667,10.84301],"type":"Point"},"id":1,"type":"Feature","properties":{"date":"2016-10-20 10:53:32","icon":"http://chart.apis.google.com/chart?chst=d_map_pin_letter&chld=1|FF0000|000000"}},
{"geometry":{"coordinates":[106.61505,10.8425083333333],"type":"Point"},"id":2,"type":"Feature","properties":{"date":"2016-10-20 10:53:52","icon":"http://chart.apis.google.com/chart?chst=d_map_pin_letter&chld=2|FF0000|000000"}},
{"geometry":{"coordinates":[106.61505,10.8425083333333],"type":"Point"},"id":3,"type":"Feature","properties":{"date":"2016-10-20 10:53:55","icon":"http://chart.apis.google.com/chart?chst=d_map_pin_letter&chld=3|FF0000|000000"}},
{"geometry":{"coordinates":[106.615241666667,10.8423583333333],"type":"Point"},"id":4,"type":"Feature","properties":{"date":"2016-10-20 10:54:06","icon":"http://chart.apis.google.com/chart?chst=d_map_pin_letter&chld=4|FF0000|000000"}},
{"geometry":{"coordinates":[106.615435,10.8423416666667],"type":"Point"},"id":5,"type":"Feature","properties":{"date":"2016-10-20 10:54:15","icon":"http://chart.apis.google.com/chart?chst=d_map_pin_letter&chld=5|FF0000|000000"}},
{"geometry":{"coordinates":[106.615435,10.8423416666667],"type":"Point"},"id":6,"type":"Feature","properties":{"date":"2016-10-20 10:54:35","icon":"http://chart.apis.google.com/chart?chst=d_map_pin_letter&chld=6|FF0000|000000"}},
{"geometry":{"coordinates":[106.615435,10.8423416666667],"type":"Point"},"id":7,"type":"Feature","properties":{"date":"2016-10-20 10:54:55","icon":"http://chart.apis.google.com/chart?chst=d_map_pin_letter&chld=7|FF0000|000000"}},
{"geometry":{"coordinates":[106.615435,10.8423416666667],"type":"Point"},"id":8,"type":"Feature","properties":{"date":"2016-10-20 10:55:15","icon":"http://chart.apis.google.com/chart?chst=d_map_pin_letter&chld=8|FF0000|000000"}},
{"geometry":{"coordinates":[106.615623333333,10.8426433333333],"type":"Point"},"id":9,"type":"Feature","properties":{"date":"2016-10-20 10:55:32","icon":"http://chart.apis.google.com/chart?chst=d_map_pin_letter&chld=9|FF0000|000000"}},
{"geometry":{"coordinates":[106.615453333333,10.842905],"type":"Point"},"id":10,"type":"Feature","properties":{"date":"2016-10-20 10:55:45","icon":"http://chart.apis.google.com/chart?chst=d_map_pin_letter&chld=10|FF0000|000000"}},
{"geometry":{"coordinates":[106.615283333333,10.8430516666667],"type":"Point"},"id":11,"type":"Feature","properties":{"date":"2016-10-20 10:55:57","icon":"http://chart.apis.google.com/chart?chst=d_map_pin_letter&chld=11|FF0000|000000"}},
{"geometry":{"coordinates":[106.614675,10.84387],"type":"Point"},"id":12,"type":"Feature","properties":{"date":"2016-10-20 10:56:17","icon":"http://chart.apis.google.com/chart?chst=d_map_pin_letter&chld=12|FF0000|000000"}},
{"geometry":{"coordinates":[106.61417,10.8446883333333],"type":"Point"},"id":13,"type":"Feature","properties":{"date":"2016-10-20 10:56:37","icon":"http://chart.apis.google.com/chart?chst=d_map_pin_letter&chld=13|FF0000|000000"}},
{"geometry":{"coordinates":[106.61253,10.8472133333333],"type":"Point"},"id":14,"type":"Feature","properties":{"date":"2016-10-20 11:00:00","icon":"http://chart.apis.google.com/chart?chst=d_map_pin_letter&chld=14|FF0000|000000"}},
{"geometry":{"coordinates":[106.61175,10.8483666666667],"type":"Point"},"id":15,"type":"Feature","properties":{"date":"2016-10-20 11:00:20","icon":"http://chart.apis.google.com/chart?chst=d_map_pin_letter&chld=15|FF0000|000000"}},
{"geometry":{"coordinates":[106.61067,10.8500483333333],"type":"Point"},"id":16,"type":"Feature","properties":{"date":"2016-10-20 11:00:40","icon":"http://chart.apis.google.com/chart?chst=d_map_pin_letter&chld=16|FF0000|000000"}},
{"geometry":{"coordinates":[106.609625,10.8516816666667],"type":"Point"},"id":17,"type":"Feature","properties":{"date":"2016-10-20 11:01:00","icon":"http://chart.apis.google.com/chart?chst=d_map_pin_letter&chld=17|FF0000|000000"}},
{"geometry":{"coordinates":[106.608778333333,10.853055],"type":"Point"},"id":18,"type":"Feature","properties":{"date":"2016-10-20 11:01:20","icon":"http://chart.apis.google.com/chart?chst=d_map_pin_letter&chld=18|FF0000|000000"}},
{"geometry":{"coordinates":[106.607875,10.8544766666667],"type":"Point"},"id":19,"type":"Feature","properties":{"date":"2016-10-20 11:01:40","icon":"http://chart.apis.google.com/chart?chst=d_map_pin_letter&chld=19|FF0000|000000"}},
{"geometry":{"coordinates":[106.607416666667,10.8551033333333],"type":"Point"},"id":20,"type":"Feature","properties":{"date":"2016-10-20 11:02:21","icon":"http://chart.apis.google.com/chart?chst=d_map_pin_letter&chld=20|FF0000|000000"}},
{"geometry":{"coordinates":[106.607416666667,10.8551033333333],"type":"Point"},"id":21,"type":"Feature","properties":{"date":"2016-10-20 11:02:41","icon":"http://chart.apis.google.com/chart?chst=d_map_pin_letter&chld=21|FF0000|000000"}},
{"geometry":{"coordinates":[106.607403333333,10.8551666666667],"type":"Point"},"id":22,"type":"Feature","properties":{"date":"2016-10-20 11:03:01","icon":"http://chart.apis.google.com/chart?chst=d_map_pin_letter&chld=22|FF0000|000000"}},
{"geometry":{"coordinates":[106.60739,10.8552016666667],"type":"Point"},"id":23,"type":"Feature","properties":{"date":"2016-10-20 11:03:02","icon":"http://chart.apis.google.com/chart?chst=d_map_pin_letter&chld=23|FF0000|000000"}},
{"geometry":{"coordinates":[106.606635,10.8563],"type":"Point"},"id":24,"type":"Feature","properties":{"date":"2016-10-20 11:03:22","icon":"http://chart.apis.google.com/chart?chst=d_map_pin_letter&chld=24|FF0000|000000"}},
{"geometry":{"coordinates":[106.60532,10.8581716666667],"type":"Point"},"id":25,"type":"Feature","properties":{"date":"2016-10-20 11:03:42","icon":"http://chart.apis.google.com/chart?chst=d_map_pin_letter&chld=25|FF0000|000000"}},
{"geometry":{"coordinates":[106.603848333333,10.86026],"type":"Point"},"id":26,"type":"Feature","properties":{"date":"2016-10-20 11:04:02","icon":"http://chart.apis.google.com/chart?chst=d_map_pin_letter&chld=26|FF0000|000000"}},
{"geometry":{"coordinates":[106.602778333333,10.8618083333333],"type":"Point"},"id":27,"type":"Feature","properties":{"date":"2016-10-20 11:04:22","icon":"http://chart.apis.google.com/chart?chst=d_map_pin_letter&chld=27|FF0000|000000"}},
{"geometry":{"coordinates":[106.60185,10.8630766666667],"type":"Point"},"id":28,"type":"Feature","properties":{"date":"2016-10-20 11:04:42","icon":"http://chart.apis.google.com/chart?chst=d_map_pin_letter&chld=28|FF0000|000000"}},
{"geometry":{"coordinates":[106.600693333333,10.86471],"type":"Point"},"id":29,"type":"Feature","properties":{"date":"2016-10-20 11:05:02","icon":"http://chart.apis.google.com/chart?chst=d_map_pin_letter&chld=29|FF0000|000000"}},
{"geometry":{"coordinates":[106.599481666667,10.8664166666667],"type":"Point"},"id":30,"type":"Feature","properties":{"date":"2016-10-20 11:05:22","icon":"http://chart.apis.google.com/chart?chst=d_map_pin_letter&chld=30|FF0000|000000"}},
{"geometry":{"coordinates":[106.598293333333,10.86808],"type":"Point"},"id":31,"type":"Feature","properties":{"date":"2016-10-20 11:05:42","icon":"http://chart.apis.google.com/chart?chst=d_map_pin_letter&chld=31|FF0000|000000"}},
{"geometry":{"coordinates":[106.597276666667,10.86953],"type":"Point"},"id":32,"type":"Feature","properties":{"date":"2016-10-20 11:06:02","icon":"http://chart.apis.google.com/chart?chst=d_map_pin_letter&chld=32|FF0000|000000"}},
{"geometry":{"coordinates":[106.59713,10.86979],"type":"Point"},"id":33,"type":"Feature","properties":{"date":"2016-10-20 11:06:12","icon":"http://chart.apis.google.com/chart?chst=d_map_pin_letter&chld=33|FF0000|000000"}},
{"geometry":{"coordinates":[106.59713,10.86979],"type":"Point"},"id":34,"type":"Feature","properties":{"date":"2016-10-20 11:06:32","icon":"http://chart.apis.google.com/chart?chst=d_map_pin_letter&chld=34|FF0000|000000"}},
{"geometry":{"coordinates":[106.59711,10.86983],"type":"Point"},"id":35,"type":"Feature","properties":{"date":"2016-10-20 11:06:37","icon":"http://chart.apis.google.com/chart?chst=d_map_pin_letter&chld=35|FF0000|000000"}},
{"geometry":{"coordinates":[106.596411666667,10.87077],"type":"Point"},"id":36,"type":"Feature","properties":{"date":"2016-10-20 11:06:57","icon":"http://chart.apis.google.com/chart?chst=d_map_pin_letter&chld=36|FF0000|000000"}},
{"geometry":{"coordinates":[106.595413333333,10.8722016666667],"type":"Point"},"id":37,"type":"Feature","properties":{"date":"2016-10-20 11:07:17","icon":"http://chart.apis.google.com/chart?chst=d_map_pin_letter&chld=37|FF0000|000000"}},
{"geometry":{"coordinates":[106.594151666667,10.8739833333333],"type":"Point"},"id":38,"type":"Feature","properties":{"date":"2016-10-20 11:07:37","icon":"http://chart.apis.google.com/chart?chst=d_map_pin_letter&chld=38|FF0000|000000"}},
{"geometry":{"coordinates":[106.593038333333,10.87564],"type":"Point"},"id":39,"type":"Feature","properties":{"date":"2016-10-20 11:07:57","icon":"http://chart.apis.google.com/chart?chst=d_map_pin_letter&chld=39|FF0000|000000"}},
{"geometry":{"coordinates":[106.591903333333,10.877225],"type":"Point"},"id":40,"type":"Feature","properties":{"date":"2016-10-20 11:08:17","icon":"http://chart.apis.google.com/chart?chst=d_map_pin_letter&chld=40|FF0000|000000"}},
{"geometry":{"coordinates":[106.590973333333,10.8784283333333],"type":"Point"},"id":41,"type":"Feature","properties":{"date":"2016-10-20 11:08:37","icon":"http://chart.apis.google.com/chart?chst=d_map_pin_letter&chld=41|FF0000|000000"}},
{"geometry":{"coordinates":[106.58972,10.8801966666667],"type":"Point"},"id":42,"type":"Feature","properties":{"date":"2016-10-20 11:08:57","icon":"http://chart.apis.google.com/chart?chst=d_map_pin_letter&chld=42|FF0000|000000"}},
{"geometry":{"coordinates":[106.588408333333,10.882065],"type":"Point"},"id":43,"type":"Feature","properties":{"date":"2016-10-20 11:09:17","icon":"http://chart.apis.google.com/chart?chst=d_map_pin_letter&chld=43|FF0000|000000"}},
{"geometry":{"coordinates":[106.587331666667,10.8836266666667],"type":"Point"},"id":44,"type":"Feature","properties":{"date":"2016-10-20 11:09:37","icon":"http://chart.apis.google.com/chart?chst=d_map_pin_letter&chld=44|FF0000|000000"}},
{"geometry":{"coordinates":[106.586806666667,10.884455],"type":"Point"},"id":45,"type":"Feature","properties":{"date":"2016-10-20 11:09:55","icon":"http://chart.apis.google.com/chart?chst=d_map_pin_letter&chld=45|FF0000|000000"}},
{"geometry":{"coordinates":[106.586735,10.88454],"type":"Point"},"id":46,"type":"Feature","properties":{"date":"2016-10-20 11:10:04","icon":"http://chart.apis.google.com/chart?chst=d_map_pin_letter&chld=46|FF0000|000000"}},
{"geometry":{"coordinates":[106.585836666667,10.885725],"type":"Point"},"id":47,"type":"Feature","properties":{"date":"2016-10-20 11:10:24","icon":"http://chart.apis.google.com/chart?chst=d_map_pin_letter&chld=47|FF0000|000000"}},
{"geometry":{"coordinates":[106.584675,10.887405],"type":"Point"},"id":48,"type":"Feature","properties":{"date":"2016-10-20 11:10:44","icon":"http://chart.apis.google.com/chart?chst=d_map_pin_letter&chld=48|FF0000|000000"}},
{"geometry":{"coordinates":[106.583523333333,10.8890716666667],"type":"Point"},"id":49,"type":"Feature","properties":{"date":"2016-10-20 11:11:04","icon":"http://chart.apis.google.com/chart?chst=d_map_pin_letter&chld=49|FF0000|000000"}},
{"geometry":{"coordinates":[106.582473333333,10.8905566666667],"type":"Point"},"id":50,"type":"Feature","properties":{"date":"2016-10-20 11:11:24","icon":"http://chart.apis.google.com/chart?chst=d_map_pin_letter&chld=50|FF0000|000000"}},
{"geometry":{"coordinates":[106.581513333333,10.89195],"type":"Point"},"id":51,"type":"Feature","properties":{"date":"2016-10-20 11:11:44","icon":"http://chart.apis.google.com/chart?chst=d_map_pin_letter&chld=51|FF0000|000000"}},
{"geometry":{"coordinates":[106.581231666667,10.8923466666667],"type":"Point"},"id":52,"type":"Feature","properties":{"date":"2016-10-20 11:11:55","icon":"http://chart.apis.google.com/chart?chst=d_map_pin_letter&chld=52|FF0000|000000"}},
{"geometry":{"coordinates":[106.581231666667,10.8923466666667],"type":"Point"},"id":53,"type":"Feature","properties":{"date":"2016-10-20 11:12:15","icon":"http://chart.apis.google.com/chart?chst=d_map_pin_letter&chld=53|FF0000|000000"}},
{"geometry":{"coordinates":[106.581166666667,10.89242],"type":"Point"},"id":54,"type":"Feature","properties":{"date":"2016-10-20 11:12:26","icon":"http://chart.apis.google.com/chart?chst=d_map_pin_letter&chld=54|FF0000|000000"}},
{"geometry":{"coordinates":[106.58093,10.8928433333333],"type":"Point"},"id":55,"type":"Feature","properties":{"date":"2016-10-20 11:12:40","icon":"http://chart.apis.google.com/chart?chst=d_map_pin_letter&chld=55|FF0000|000000"}},
{"geometry":{"coordinates":[106.580871666667,10.8928866666667],"type":"Point"},"id":56,"type":"Feature","properties":{"date":"2016-10-20 11:12:59","icon":"http://chart.apis.google.com/chart?chst=d_map_pin_letter&chld=56|FF0000|000000"}},
{"geometry":{"coordinates":[106.580053333333,10.8940933333333],"type":"Point"},"id":57,"type":"Feature","properties":{"date":"2016-10-20 11:13:19","icon":"http://chart.apis.google.com/chart?chst=d_map_pin_letter&chld=57|FF0000|000000"}},
{"geometry":{"coordinates":[106.578865,10.8957183333333],"type":"Point"},"id":58,"type":"Feature","properties":{"date":"2016-10-20 11:13:39","icon":"http://chart.apis.google.com/chart?chst=d_map_pin_letter&chld=58|FF0000|000000"}},
{"geometry":{"coordinates":[106.577651666667,10.897465],"type":"Point"},"id":59,"type":"Feature","properties":{"date":"2016-10-20 11:13:59","icon":"http://chart.apis.google.com/chart?chst=d_map_pin_letter&chld=59|FF0000|000000"}},
{"geometry":{"coordinates":[106.576378333333,10.8992783333333],"type":"Point"},"id":60,"type":"Feature","properties":{"date":"2016-10-20 11:14:19","icon":"http://chart.apis.google.com/chart?chst=d_map_pin_letter&chld=60|FF0000|000000"}},
{"geometry":{"coordinates":[106.575965,10.8999066666667],"type":"Point"},"id":61,"type":"Feature","properties":{"date":"2016-10-20 11:14:33","icon":"http://chart.apis.google.com/chart?chst=d_map_pin_letter&chld=61|FF0000|000000"}},
{"geometry":{"coordinates":[106.575873333333,10.90001],"type":"Point"},"id":62,"type":"Feature","properties":{"date":"2016-10-20 11:14:52","icon":"http://chart.apis.google.com/chart?chst=d_map_pin_letter&chld=62|FF0000|000000"}},
{"geometry":{"coordinates":[106.575003333333,10.9012883333333],"type":"Point"},"id":63,"type":"Feature","properties":{"date":"2016-10-20 11:15:12","icon":"http://chart.apis.google.com/chart?chst=d_map_pin_letter&chld=63|FF0000|000000"}},
{"geometry":{"coordinates":[106.573466666667,10.9034733333333],"type":"Point"},"id":64,"type":"Feature","properties":{"date":"2016-10-20 11:15:32","icon":"http://chart.apis.google.com/chart?chst=d_map_pin_letter&chld=64|FF0000|000000"}},
{"geometry":{"coordinates":[106.571725,10.9058566666667],"type":"Point"},"id":65,"type":"Feature","properties":{"date":"2016-10-20 11:15:52","icon":"http://chart.apis.google.com/chart?chst=d_map_pin_letter&chld=65|FF0000|000000"}},
{"geometry":{"coordinates":[106.570028333333,10.9082566666667],"type":"Point"},"id":66,"type":"Feature","properties":{"date":"2016-10-20 11:16:12","icon":"http://chart.apis.google.com/chart?chst=d_map_pin_letter&chld=66|FF0000|000000"}},
{"geometry":{"coordinates":[106.568393333333,10.9106033333333],"type":"Point"},"id":67,"type":"Feature","properties":{"date":"2016-10-20 11:16:32","icon":"http://chart.apis.google.com/chart?chst=d_map_pin_letter&chld=67|FF0000|000000"}},
{"geometry":{"coordinates":[106.566911666667,10.91269],"type":"Point"},"id":68,"type":"Feature","properties":{"date":"2016-10-20 11:16:52","icon":"http://chart.apis.google.com/chart?chst=d_map_pin_letter&chld=68|FF0000|000000"}},
{"geometry":{"coordinates":[106.565421666667,10.9148116666667],"type":"Point"},"id":69,"type":"Feature","properties":{"date":"2016-10-20 11:17:12","icon":"http://chart.apis.google.com/chart?chst=d_map_pin_letter&chld=69|FF0000|000000"}},
{"geometry":{"coordinates":[106.56413,10.9167033333333],"type":"Point"},"id":70,"type":"Feature","properties":{"date":"2016-10-20 11:17:32","icon":"http://chart.apis.google.com/chart?chst=d_map_pin_letter&chld=70|FF0000|000000"}},
{"geometry":{"coordinates":[106.563938333333,10.9170266666667],"type":"Point"},"id":71,"type":"Feature","properties":{"date":"2016-10-20 11:17:41","icon":"http://chart.apis.google.com/chart?chst=d_map_pin_letter&chld=71|FF0000|000000"}},
{"geometry":{"coordinates":[106.563906666667,10.9170733333333],"type":"Point"},"id":72,"type":"Feature","properties":{"date":"2016-10-20 11:17:52","icon":"http://chart.apis.google.com/chart?chst=d_map_pin_letter&chld=72|FF0000|000000"}},
{"geometry":{"coordinates":[106.563106666667,10.9181816666667],"type":"Point"},"id":73,"type":"Feature","properties":{"date":"2016-10-20 11:18:12","icon":"http://chart.apis.google.com/chart?chst=d_map_pin_letter&chld=73|FF0000|000000"}},
{"geometry":{"coordinates":[106.561508333333,10.9204633333333],"type":"Point"},"id":74,"type":"Feature","properties":{"date":"2016-10-20 11:18:32","icon":"http://chart.apis.google.com/chart?chst=d_map_pin_letter&chld=74|FF0000|000000"}},
{"geometry":{"coordinates":[106.559413333333,10.923395],"type":"Point"},"id":75,"type":"Feature","properties":{"date":"2016-10-20 11:18:52","icon":"http://chart.apis.google.com/chart?chst=d_map_pin_letter&chld=75|FF0000|000000"}},
{"geometry":{"coordinates":[106.557961666667,10.9254966666667],"type":"Point"},"id":76,"type":"Feature","properties":{"date":"2016-10-20 11:19:12","icon":"http://chart.apis.google.com/chart?chst=d_map_pin_letter&chld=76|FF0000|000000"}},
{"geometry":{"coordinates":[106.556895,10.9271333333333],"type":"Point"},"id":77,"type":"Feature","properties":{"date":"2016-10-20 11:19:32","icon":"http://chart.apis.google.com/chart?chst=d_map_pin_letter&chld=77|FF0000|000000"}},
{"geometry":{"coordinates":[106.55669,10.927455],"type":"Point"},"id":78,"type":"Feature","properties":{"date":"2016-10-20 11:19:41","icon":"http://chart.apis.google.com/chart?chst=d_map_pin_letter&chld=78|FF0000|000000"}},
{"geometry":{"coordinates":[106.556625,10.9275366666667],"type":"Point"},"id":79,"type":"Feature","properties":{"date":"2016-10-20 11:19:53","icon":"http://chart.apis.google.com/chart?chst=d_map_pin_letter&chld=79|FF0000|000000"}},
{"geometry":{"coordinates":[106.55565,10.9288533333333],"type":"Point"},"id":80,"type":"Feature","properties":{"date":"2016-10-20 11:20:13","icon":"http://chart.apis.google.com/chart?chst=d_map_pin_letter&chld=80|FF0000|000000"}},
{"geometry":{"coordinates":[106.554093333333,10.9307333333333],"type":"Point"},"id":81,"type":"Feature","properties":{"date":"2016-10-20 11:20:33","icon":"http://chart.apis.google.com/chart?chst=d_map_pin_letter&chld=81|FF0000|000000"}},
{"geometry":{"coordinates":[106.552191666667,10.9328383333333],"type":"Point"},"id":82,"type":"Feature","properties":{"date":"2016-10-20 11:20:53","icon":"http://chart.apis.google.com/chart?chst=d_map_pin_letter&chld=82|FF0000|000000"}},
{"geometry":{"coordinates":[106.551143333333,10.9339683333333],"type":"Point"},"id":83,"type":"Feature","properties":{"date":"2016-10-20 11:21:13","icon":"http://chart.apis.google.com/chart?chst=d_map_pin_letter&chld=83|FF0000|000000"}},
{"geometry":{"coordinates":[106.550251666667,10.9345866666667],"type":"Point"},"id":84,"type":"Feature","properties":{"date":"2016-10-20 11:21:29","icon":"http://chart.apis.google.com/chart?chst=d_map_pin_letter&chld=84|FF0000|000000"}},
{"geometry":{"coordinates":[106.550251666667,10.9345866666667],"type":"Point"},"id":85,"type":"Feature","properties":{"date":"2016-10-20 11:21:49","icon":"http://chart.apis.google.com/chart?chst=d_map_pin_letter&chld=85|FF0000|000000"}},
{"geometry":{"coordinates":[106.550251666667,10.9345866666667],"type":"Point"},"id":86,"type":"Feature","properties":{"date":"2016-10-20 11:22:09","icon":"http://chart.apis.google.com/chart?chst=d_map_pin_letter&chld=86|FF0000|000000"}},
{"geometry":{"coordinates":[106.550055,10.934665],"type":"Point"},"id":87,"type":"Feature","properties":{"date":"2016-10-20 11:22:30","icon":"http://chart.apis.google.com/chart?chst=d_map_pin_letter&chld=87|FF0000|000000"}},
{"geometry":{"coordinates":[106.548598333333,10.9353483333333],"type":"Point"},"id":88,"type":"Feature","properties":{"date":"2016-10-20 11:22:50","icon":"http://chart.apis.google.com/chart?chst=d_map_pin_letter&chld=88|FF0000|000000"}},
{"geometry":{"coordinates":[106.546323333333,10.9364566666667],"type":"Point"},"id":89,"type":"Feature","properties":{"date":"2016-10-20 11:23:10","icon":"http://chart.apis.google.com/chart?chst=d_map_pin_letter&chld=89|FF0000|000000"}},
{"geometry":{"coordinates":[106.543745,10.9377133333333],"type":"Point"},"id":90,"type":"Feature","properties":{"date":"2016-10-20 11:23:30","icon":"http://chart.apis.google.com/chart?chst=d_map_pin_letter&chld=90|FF0000|000000"}},
{"geometry":{"coordinates":[106.54192,10.938605],"type":"Point"},"id":91,"type":"Feature","properties":{"date":"2016-10-20 11:23:50","icon":"http://chart.apis.google.com/chart?chst=d_map_pin_letter&chld=91|FF0000|000000"}},
{"geometry":{"coordinates":[106.54152,10.9388016666667],"type":"Point"},"id":92,"type":"Feature","properties":{"date":"2016-10-20 11:24:02","icon":"http://chart.apis.google.com/chart?chst=d_map_pin_letter&chld=92|FF0000|000000"}},
{"geometry":{"coordinates":[106.541391666667,10.938865],"type":"Point"},"id":93,"type":"Feature","properties":{"date":"2016-10-20 11:24:22","icon":"http://chart.apis.google.com/chart?chst=d_map_pin_letter&chld=93|FF0000|000000"}},
{"geometry":{"coordinates":[106.54003,10.939535],"type":"Point"},"id":94,"type":"Feature","properties":{"date":"2016-10-20 11:24:42","icon":"http://chart.apis.google.com/chart?chst=d_map_pin_letter&chld=94|FF0000|000000"}},
{"geometry":{"coordinates":[106.537536666667,10.94075],"type":"Point"},"id":95,"type":"Feature","properties":{"date":"2016-10-20 11:25:02","icon":"http://chart.apis.google.com/chart?chst=d_map_pin_letter&chld=95|FF0000|000000"}},
{"geometry":{"coordinates":[106.536656666667,10.9411666666667],"type":"Point"},"id":96,"type":"Feature","properties":{"date":"2016-10-20 11:25:09","icon":"http://chart.apis.google.com/chart?chst=d_map_pin_letter&chld=96|FF0000|000000"}},
{"geometry":{"coordinates":[106.536558333333,10.9412166666667],"type":"Point"},"id":97,"type":"Feature","properties":{"date":"2016-10-20 11:25:10","icon":"http://chart.apis.google.com/chart?chst=d_map_pin_letter&chld=97|FF0000|000000"}},
{"geometry":{"coordinates":[106.53621,10.9413866666667],"type":"Point"},"id":98,"type":"Feature","properties":{"date":"2016-10-20 11:25:17","icon":"http://chart.apis.google.com/chart?chst=d_map_pin_letter&chld=98|FF0000|000000"}},
{"geometry":{"coordinates":[106.536111666667,10.941435],"type":"Point"},"id":99,"type":"Feature","properties":{"date":"2016-10-20 11:25:22","icon":"http://chart.apis.google.com/chart?chst=d_map_pin_letter&chld=99|FF0000|000000"}},
{"geometry":{"coordinates":[106.5346,10.94216],"type":"Point"},"id":100,"type":"Feature","properties":{"date":"2016-10-20 11:25:42","icon":"http://chart.apis.google.com/chart?chst=d_map_pin_letter&chld=100|FF0000|000000"}},
{"geometry":{"coordinates":[106.532123333333,10.9433633333333],"type":"Point"},"id":101,"type":"Feature","properties":{"date":"2016-10-20 11:26:02","icon":"http://chart.apis.google.com/chart?chst=d_map_pin_letter&chld=101|FF0000|000000"}},
{"geometry":{"coordinates":[106.530703333333,10.9440433333333],"type":"Point"},"id":102,"type":"Feature","properties":{"date":"2016-10-20 11:26:22","icon":"http://chart.apis.google.com/chart?chst=d_map_pin_letter&chld=102|FF0000|000000"}},
{"geometry":{"coordinates":[106.529428333333,10.9446466666667],"type":"Point"},"id":103,"type":"Feature","properties":{"date":"2016-10-20 11:26:42","icon":"http://chart.apis.google.com/chart?chst=d_map_pin_letter&chld=103|FF0000|000000"}},
{"geometry":{"coordinates":[106.527051666667,10.9458116666667],"type":"Point"},"id":104,"type":"Feature","properties":{"date":"2016-10-20 11:27:02","icon":"http://chart.apis.google.com/chart?chst=d_map_pin_letter&chld=104|FF0000|000000"}},
{"geometry":{"coordinates":[106.52448,10.947145],"type":"Point"},"id":105,"type":"Feature","properties":{"date":"2016-10-20 11:27:22","icon":"http://chart.apis.google.com/chart?chst=d_map_pin_letter&chld=105|FF0000|000000"}},
{"geometry":{"coordinates":[106.524421666667,10.94717],"type":"Point"},"id":106,"type":"Feature","properties":{"date":"2016-10-20 11:27:27","icon":"http://chart.apis.google.com/chart?chst=d_map_pin_letter&chld=106|FF0000|000000"}},
{"geometry":{"coordinates":[106.524345,10.9471983333333],"type":"Point"},"id":107,"type":"Feature","properties":{"date":"2016-10-20 11:27:45","icon":"http://chart.apis.google.com/chart?chst=d_map_pin_letter&chld=107|FF0000|000000"}},
{"geometry":{"coordinates":[106.523493333333,10.9477566666667],"type":"Point"},"id":108,"type":"Feature","properties":{"date":"2016-10-20 11:28:05","icon":"http://chart.apis.google.com/chart?chst=d_map_pin_letter&chld=108|FF0000|000000"}},
{"geometry":{"coordinates":[106.521886666667,10.9488316666667],"type":"Point"},"id":109,"type":"Feature","properties":{"date":"2016-10-20 11:28:25","icon":"http://chart.apis.google.com/chart?chst=d_map_pin_letter&chld=109|FF0000|000000"}},
{"geometry":{"coordinates":[106.519995,10.9501083333333],"type":"Point"},"id":110,"type":"Feature","properties":{"date":"2016-10-20 11:28:45","icon":"http://chart.apis.google.com/chart?chst=d_map_pin_letter&chld=110|FF0000|000000"}},
{"geometry":{"coordinates":[106.517666666667,10.9517316666667],"type":"Point"},"id":111,"type":"Feature","properties":{"date":"2016-10-20 11:29:05","icon":"http://chart.apis.google.com/chart?chst=d_map_pin_letter&chld=111|FF0000|000000"}},
{"geometry":{"coordinates":[106.515056666667,10.953525],"type":"Point"},"id":112,"type":"Feature","properties":{"date":"2016-10-20 11:29:25","icon":"http://chart.apis.google.com/chart?chst=d_map_pin_letter&chld=112|FF0000|000000"}},
{"geometry":{"coordinates":[106.513526666667,10.95457],"type":"Point"},"id":113,"type":"Feature","properties":{"date":"2016-10-20 11:29:45","icon":"http://chart.apis.google.com/chart?chst=d_map_pin_letter&chld=113|FF0000|000000"}},
{"geometry":{"coordinates":[106.512385,10.9553516666667],"type":"Point"},"id":114,"type":"Feature","properties":{"date":"2016-10-20 11:30:05","icon":"http://chart.apis.google.com/chart?chst=d_map_pin_letter&chld=114|FF0000|000000"}},
{"geometry":{"coordinates":[106.510698333333,10.956465],"type":"Point"},"id":115,"type":"Feature","properties":{"date":"2016-10-20 11:30:25","icon":"http://chart.apis.google.com/chart?chst=d_map_pin_letter&chld=115|FF0000|000000"}},
{"geometry":{"coordinates":[106.508766666667,10.957525],"type":"Point"},"id":116,"type":"Feature","properties":{"date":"2016-10-20 11:30:45","icon":"http://chart.apis.google.com/chart?chst=d_map_pin_letter&chld=116|FF0000|000000"}},
{"geometry":{"coordinates":[106.506178333333,10.95887],"type":"Point"},"id":117,"type":"Feature","properties":{"date":"2016-10-20 11:31:05","icon":"http://chart.apis.google.com/chart?chst=d_map_pin_letter&chld=117|FF0000|000000"}},
{"geometry":{"coordinates":[106.50562,10.95918],"type":"Point"},"id":118,"type":"Feature","properties":{"date":"2016-10-20 11:31:16","icon":"http://chart.apis.google.com/chart?chst=d_map_pin_letter&chld=118|FF0000|000000"}},
{"geometry":{"coordinates":[106.50554,10.9592216666667],"type":"Point"},"id":119,"type":"Feature","properties":{"date":"2016-10-20 11:31:20","icon":"http://chart.apis.google.com/chart?chst=d_map_pin_letter&chld=119|FF0000|000000"}},
{"geometry":{"coordinates":[106.504121666667,10.959915],"type":"Point"},"id":120,"type":"Feature","properties":{"date":"2016-10-20 11:31:40","icon":"http://chart.apis.google.com/chart?chst=d_map_pin_letter&chld=120|FF0000|000000"}},
{"geometry":{"coordinates":[106.503028333333,10.9604616666667],"type":"Point"},"id":121,"type":"Feature","properties":{"date":"2016-10-20 11:31:57","icon":"http://chart.apis.google.com/chart?chst=d_map_pin_letter&chld=121|FF0000|000000"}},
{"geometry":{"coordinates":[106.50298,10.9604916666667],"type":"Point"},"id":122,"type":"Feature","properties":{"date":"2016-10-20 11:32:17","icon":"http://chart.apis.google.com/chart?chst=d_map_pin_letter&chld=122|FF0000|000000"}},
{"geometry":{"coordinates":[106.502218333333,10.960935],"type":"Point"},"id":123,"type":"Feature","properties":{"date":"2016-10-20 11:32:37","icon":"http://chart.apis.google.com/chart?chst=d_map_pin_letter&chld=123|FF0000|000000"}},
{"geometry":{"coordinates":[106.502218333333,10.960935],"type":"Point"},"id":124,"type":"Feature","properties":{"date":"2016-10-20 11:32:40","icon":"http://chart.apis.google.com/chart?chst=d_map_pin_letter&chld=124|FF0000|000000"}},
{"geometry":{"coordinates":[106.50212,10.960975],"type":"Point"},"id":125,"type":"Feature","properties":{"date":"2016-10-20 11:32:45","icon":"http://chart.apis.google.com/chart?chst=d_map_pin_letter&chld=125|FF0000|000000"}},
{"geometry":{"coordinates":[106.500698333333,10.961765],"type":"Point"},"id":126,"type":"Feature","properties":{"date":"2016-10-20 11:33:05","icon":"http://chart.apis.google.com/chart?chst=d_map_pin_letter&chld=126|FF0000|000000"}},
{"geometry":{"coordinates":[106.498493333333,10.96302],"type":"Point"},"id":127,"type":"Feature","properties":{"date":"2016-10-20 11:33:25","icon":"http://chart.apis.google.com/chart?chst=d_map_pin_letter&chld=127|FF0000|000000"}},
{"geometry":{"coordinates":[106.496206666667,10.964345],"type":"Point"},"id":128,"type":"Feature","properties":{"date":"2016-10-20 11:33:45","icon":"http://chart.apis.google.com/chart?chst=d_map_pin_letter&chld=128|FF0000|000000"}},
{"geometry":{"coordinates":[106.493913333333,10.96539],"type":"Point"},"id":129,"type":"Feature","properties":{"date":"2016-10-20 11:34:05","icon":"http://chart.apis.google.com/chart?chst=d_map_pin_letter&chld=129|FF0000|000000"}},
{"geometry":{"coordinates":[106.492056666667,10.9661083333333],"type":"Point"},"id":130,"type":"Feature","properties":{"date":"2016-10-20 11:34:25","icon":"http://chart.apis.google.com/chart?chst=d_map_pin_letter&chld=130|FF0000|000000"}},
{"geometry":{"coordinates":[106.489923333333,10.9669583333333],"type":"Point"},"id":131,"type":"Feature","properties":{"date":"2016-10-20 11:34:45","icon":"http://chart.apis.google.com/chart?chst=d_map_pin_letter&chld=131|FF0000|000000"}},
{"geometry":{"coordinates":[106.488403333333,10.9675783333333],"type":"Point"},"id":132,"type":"Feature","properties":{"date":"2016-10-20 11:35:05","icon":"http://chart.apis.google.com/chart?chst=d_map_pin_letter&chld=132|FF0000|000000"}},
{"geometry":{"coordinates":[106.488301666667,10.9676033333333],"type":"Point"},"id":133,"type":"Feature","properties":{"date":"2016-10-20 11:35:11","icon":"http://chart.apis.google.com/chart?chst=d_map_pin_letter&chld=133|FF0000|000000"}},
{"geometry":{"coordinates":[106.486913333333,10.9680283333333],"type":"Point"},"id":134,"type":"Feature","properties":{"date":"2016-10-20 11:35:31","icon":"http://chart.apis.google.com/chart?chst=d_map_pin_letter&chld=134|FF0000|000000"}},
{"geometry":{"coordinates":[106.485128333333,10.968875],"type":"Point"},"id":135,"type":"Feature","properties":{"date":"2016-10-20 11:35:51","icon":"http://chart.apis.google.com/chart?chst=d_map_pin_letter&chld=135|FF0000|000000"}},
{"geometry":{"coordinates":[106.483118333333,10.9701783333333],"type":"Point"},"id":136,"type":"Feature","properties":{"date":"2016-10-20 11:36:11","icon":"http://chart.apis.google.com/chart?chst=d_map_pin_letter&chld=136|FF0000|000000"}},
{"geometry":{"coordinates":[106.48189,10.97123],"type":"Point"},"id":137,"type":"Feature","properties":{"date":"2016-10-20 11:36:31","icon":"http://chart.apis.google.com/chart?chst=d_map_pin_letter&chld=137|FF0000|000000"}}
]}