{
 "type": "FeatureCollection",
"features": [
{"geometry":{"coordinates":[106.481945,10.9714633333333],"type":"Point"},"id":0,"type":"Feature","properties":{"date":"2016-10-08 08:40:48","icon":"http://chart.apis.google.com/chart?chst=d_map_pin_letter&chld=0|FF0000|000000"}},
{"geometry":{"coordinates":[106.481771666667,10.9714183333333],"type":"Point"},"id":1,"type":"Feature","properties":{"date":"2016-10-08 08:41:00","icon":"http://chart.apis.google.com/chart?chst=d_map_pin_letter&chld=1|FF0000|000000"}},
{"geometry":{"coordinates":[106.481771666667,10.9714183333333],"type":"Point"},"id":2,"type":"Feature","properties":{"date":"2016-10-08 08:41:20","icon":"http://chart.apis.google.com/chart?chst=d_map_pin_letter&chld=2|FF0000|000000"}},
{"geometry":{"coordinates":[106.481771666667,10.9714183333333],"type":"Point"},"id":3,"type":"Feature","properties":{"date":"2016-10-08 08:41:40","icon":"http://chart.apis.google.com/chart?chst=d_map_pin_letter&chld=3|FF0000|000000"}},
{"geometry":{"coordinates":[106.481535,10.9712366666667],"type":"Point"},"id":4,"type":"Feature","properties":{"date":"2016-10-08 08:41:51","icon":"http://chart.apis.google.com/chart?chst=d_map_pin_letter&chld=4|FF0000|000000"}},
{"geometry":{"coordinates":[106.481876666667,10.9709266666667],"type":"Point"},"id":5,"type":"Feature","properties":{"date":"2016-10-08 08:42:11","icon":"http://chart.apis.google.com/chart?chst=d_map_pin_letter&chld=5|FF0000|000000"}},
{"geometry":{"coordinates":[106.481876666667,10.9709266666667],"type":"Point"},"id":6,"type":"Feature","properties":{"date":"2016-10-08 08:42:14","icon":"http://chart.apis.google.com/chart?chst=d_map_pin_letter&chld=6|FF0000|000000"}},
{"geometry":{"coordinates":[106.482015,10.970825],"type":"Point"},"id":7,"type":"Feature","properties":{"date":"2016-10-08 08:42:21","icon":"http://chart.apis.google.com/chart?chst=d_map_pin_letter&chld=7|FF0000|000000"}},
{"geometry":{"coordinates":[106.48203,10.9708133333333],"type":"Point"},"id":8,"type":"Feature","properties":{"date":"2016-10-08 08:42:22","icon":"http://chart.apis.google.com/chart?chst=d_map_pin_letter&chld=8|FF0000|000000"}},
{"geometry":{"coordinates":[106.482045,10.9708016666667],"type":"Point"},"id":9,"type":"Feature","properties":{"date":"2016-10-08 08:42:23","icon":"http://chart.apis.google.com/chart?chst=d_map_pin_letter&chld=9|FF0000|000000"}},
{"geometry":{"coordinates":[106.482108333333,10.9707433333333],"type":"Point"},"id":10,"type":"Feature","properties":{"date":"2016-10-08 08:42:31","icon":"http://chart.apis.google.com/chart?chst=d_map_pin_letter&chld=10|FF0000|000000"}},
{"geometry":{"coordinates":[106.482238333333,10.9706783333333],"type":"Point"},"id":11,"type":"Feature","properties":{"date":"2016-10-08 08:42:51","icon":"http://chart.apis.google.com/chart?chst=d_map_pin_letter&chld=11|FF0000|000000"}},
{"geometry":{"coordinates":[106.48237,10.9705866666667],"type":"Point"},"id":12,"type":"Feature","properties":{"date":"2016-10-08 08:42:56","icon":"http://chart.apis.google.com/chart?chst=d_map_pin_letter&chld=12|FF0000|000000"}},
{"geometry":{"coordinates":[106.482791666667,10.9702783333333],"type":"Point"},"id":13,"type":"Feature","properties":{"date":"2016-10-08 08:43:16","icon":"http://chart.apis.google.com/chart?chst=d_map_pin_letter&chld=13|FF0000|000000"}},
{"geometry":{"coordinates":[106.483618333333,10.9697633333333],"type":"Point"},"id":14,"type":"Feature","properties":{"date":"2016-10-08 08:43:36","icon":"http://chart.apis.google.com/chart?chst=d_map_pin_letter&chld=14|FF0000|000000"}},
{"geometry":{"coordinates":[106.48451,10.9691216666667],"type":"Point"},"id":15,"type":"Feature","properties":{"date":"2016-10-08 08:43:56","icon":"http://chart.apis.google.com/chart?chst=d_map_pin_letter&chld=15|FF0000|000000"}},
{"geometry":{"coordinates":[106.48583,10.9682866666667],"type":"Point"},"id":16,"type":"Feature","properties":{"date":"2016-10-08 08:44:16","icon":"http://chart.apis.google.com/chart?chst=d_map_pin_letter&chld=16|FF0000|000000"}},
{"geometry":{"coordinates":[106.486288333333,10.9681233333333],"type":"Point"},"id":17,"type":"Feature","properties":{"date":"2016-10-08 08:44:28","icon":"http://chart.apis.google.com/chart?chst=d_map_pin_letter&chld=17|FF0000|000000"}},
{"geometry":{"coordinates":[106.486471666667,10.96806],"type":"Point"},"id":18,"type":"Feature","properties":{"date":"2016-10-08 08:44:36","icon":"http://chart.apis.google.com/chart?chst=d_map_pin_letter&chld=18|FF0000|000000"}},
{"geometry":{"coordinates":[106.488131666667,10.9674983333333],"type":"Point"},"id":19,"type":"Feature","properties":{"date":"2016-10-08 08:44:56","icon":"http://chart.apis.google.com/chart?chst=d_map_pin_letter&chld=19|FF0000|000000"}},
{"geometry":{"coordinates":[106.488951666667,10.967185],"type":"Point"},"id":20,"type":"Feature","properties":{"date":"2016-10-08 08:45:10","icon":"http://chart.apis.google.com/chart?chst=d_map_pin_letter&chld=20|FF0000|000000"}},
{"geometry":{"coordinates":[106.489068333333,10.9671433333333],"type":"Point"},"id":21,"type":"Feature","properties":{"date":"2016-10-08 08:45:15","icon":"http://chart.apis.google.com/chart?chst=d_map_pin_letter&chld=21|FF0000|000000"}},
{"geometry":{"coordinates":[106.490703333333,10.9665216666667],"type":"Point"},"id":22,"type":"Feature","properties":{"date":"2016-10-08 08:45:35","icon":"http://chart.apis.google.com/chart?chst=d_map_pin_letter&chld=22|FF0000|000000"}},
{"geometry":{"coordinates":[106.493015,10.9656183333333],"type":"Point"},"id":23,"type":"Feature","properties":{"date":"2016-10-08 08:45:55","icon":"http://chart.apis.google.com/chart?chst=d_map_pin_letter&chld=23|FF0000|000000"}},
{"geometry":{"coordinates":[106.495048333333,10.9647966666667],"type":"Point"},"id":24,"type":"Feature","properties":{"date":"2016-10-08 08:46:15","icon":"http://chart.apis.google.com/chart?chst=d_map_pin_letter&chld=24|FF0000|000000"}},
{"geometry":{"coordinates":[106.495496666667,10.9645883333333],"type":"Point"},"id":25,"type":"Feature","properties":{"date":"2016-10-08 08:46:28","icon":"http://chart.apis.google.com/chart?chst=d_map_pin_letter&chld=25|FF0000|000000"}},
{"geometry":{"coordinates":[106.495496666667,10.9645883333333],"type":"Point"},"id":26,"type":"Feature","properties":{"date":"2016-10-08 08:46:48","icon":"http://chart.apis.google.com/chart?chst=d_map_pin_letter&chld=26|FF0000|000000"}},
{"geometry":{"coordinates":[106.4957,10.964475],"type":"Point"},"id":27,"type":"Feature","properties":{"date":"2016-10-08 08:47:01","icon":"http://chart.apis.google.com/chart?chst=d_map_pin_letter&chld=27|FF0000|000000"}},
{"geometry":{"coordinates":[106.496925,10.9637966666667],"type":"Point"},"id":28,"type":"Feature","properties":{"date":"2016-10-08 08:47:21","icon":"http://chart.apis.google.com/chart?chst=d_map_pin_letter&chld=28|FF0000|000000"}},
{"geometry":{"coordinates":[106.498705,10.962775],"type":"Point"},"id":29,"type":"Feature","properties":{"date":"2016-10-08 08:47:41","icon":"http://chart.apis.google.com/chart?chst=d_map_pin_letter&chld=29|FF0000|000000"}},
{"geometry":{"coordinates":[106.5005,10.9617383333333],"type":"Point"},"id":30,"type":"Feature","properties":{"date":"2016-10-08 08:48:01","icon":"http://chart.apis.google.com/chart?chst=d_map_pin_letter&chld=30|FF0000|000000"}},
{"geometry":{"coordinates":[106.502018333333,10.96086],"type":"Point"},"id":31,"type":"Feature","properties":{"date":"2016-10-08 08:48:21","icon":"http://chart.apis.google.com/chart?chst=d_map_pin_letter&chld=31|FF0000|000000"}},
{"geometry":{"coordinates":[106.50472,10.9594833333333],"type":"Point"},"id":32,"type":"Feature","properties":{"date":"2016-10-08 08:49:01","icon":"http://chart.apis.google.com/chart?chst=d_map_pin_letter&chld=32|FF0000|000000"}},
{"geometry":{"coordinates":[106.505068333333,10.95927],"type":"Point"},"id":33,"type":"Feature","properties":{"date":"2016-10-08 08:49:12","icon":"http://chart.apis.google.com/chart?chst=d_map_pin_letter&chld=33|FF0000|000000"}},
{"geometry":{"coordinates":[106.505223333333,10.9592016666667],"type":"Point"},"id":34,"type":"Feature","properties":{"date":"2016-10-08 08:49:21","icon":"http://chart.apis.google.com/chart?chst=d_map_pin_letter&chld=34|FF0000|000000"}},
{"geometry":{"coordinates":[106.50642,10.9586],"type":"Point"},"id":35,"type":"Feature","properties":{"date":"2016-10-08 08:49:41","icon":"http://chart.apis.google.com/chart?chst=d_map_pin_letter&chld=35|FF0000|000000"}},
{"geometry":{"coordinates":[106.507926666667,10.9578383333333],"type":"Point"},"id":36,"type":"Feature","properties":{"date":"2016-10-08 08:50:01","icon":"http://chart.apis.google.com/chart?chst=d_map_pin_letter&chld=36|FF0000|000000"}},
{"geometry":{"coordinates":[106.5094,10.9570683333333],"type":"Point"},"id":37,"type":"Feature","properties":{"date":"2016-10-08 08:50:21","icon":"http://chart.apis.google.com/chart?chst=d_map_pin_letter&chld=37|FF0000|000000"}},
{"geometry":{"coordinates":[106.510015,10.9567233333333],"type":"Point"},"id":38,"type":"Feature","properties":{"date":"2016-10-08 08:50:40","icon":"http://chart.apis.google.com/chart?chst=d_map_pin_letter&chld=38|FF0000|000000"}},
{"geometry":{"coordinates":[106.510141666667,10.9566633333333],"type":"Point"},"id":39,"type":"Feature","properties":{"date":"2016-10-08 08:50:47","icon":"http://chart.apis.google.com/chart?chst=d_map_pin_letter&chld=39|FF0000|000000"}},
{"geometry":{"coordinates":[106.51127,10.9559833333333],"type":"Point"},"id":40,"type":"Feature","properties":{"date":"2016-10-08 08:51:07","icon":"http://chart.apis.google.com/chart?chst=d_map_pin_letter&chld=40|FF0000|000000"}},
{"geometry":{"coordinates":[106.512431666667,10.9551583333333],"type":"Point"},"id":41,"type":"Feature","properties":{"date":"2016-10-08 08:51:27","icon":"http://chart.apis.google.com/chart?chst=d_map_pin_letter&chld=41|FF0000|000000"}},
{"geometry":{"coordinates":[106.513693333333,10.95429],"type":"Point"},"id":42,"type":"Feature","properties":{"date":"2016-10-08 08:51:47","icon":"http://chart.apis.google.com/chart?chst=d_map_pin_letter&chld=42|FF0000|000000"}},
{"geometry":{"coordinates":[106.51511,10.953325],"type":"Point"},"id":43,"type":"Feature","properties":{"date":"2016-10-08 08:52:07","icon":"http://chart.apis.google.com/chart?chst=d_map_pin_letter&chld=43|FF0000|000000"}},
{"geometry":{"coordinates":[106.5158,10.9528583333333],"type":"Point"},"id":44,"type":"Feature","properties":{"date":"2016-10-08 08:52:27","icon":"http://chart.apis.google.com/chart?chst=d_map_pin_letter&chld=44|FF0000|000000"}},
{"geometry":{"coordinates":[106.517208333333,10.9519016666667],"type":"Point"},"id":45,"type":"Feature","properties":{"date":"2016-10-08 08:52:47","icon":"http://chart.apis.google.com/chart?chst=d_map_pin_letter&chld=45|FF0000|000000"}},
{"geometry":{"coordinates":[106.518855,10.9507833333333],"type":"Point"},"id":46,"type":"Feature","properties":{"date":"2016-10-08 08:53:07","icon":"http://chart.apis.google.com/chart?chst=d_map_pin_letter&chld=46|FF0000|000000"}},
{"geometry":{"coordinates":[106.519611666667,10.95028],"type":"Point"},"id":47,"type":"Feature","properties":{"date":"2016-10-08 08:53:27","icon":"http://chart.apis.google.com/chart?chst=d_map_pin_letter&chld=47|FF0000|000000"}},
{"geometry":{"coordinates":[106.521345,10.9490916666667],"type":"Point"},"id":48,"type":"Feature","properties":{"date":"2016-10-08 08:53:47","icon":"http://chart.apis.google.com/chart?chst=d_map_pin_letter&chld=48|FF0000|000000"}},
{"geometry":{"coordinates":[106.52297,10.947965],"type":"Point"},"id":49,"type":"Feature","properties":{"date":"2016-10-08 08:54:07","icon":"http://chart.apis.google.com/chart?chst=d_map_pin_letter&chld=49|FF0000|000000"}},
{"geometry":{"coordinates":[106.52325,10.9477433333333],"type":"Point"},"id":50,"type":"Feature","properties":{"date":"2016-10-08 08:54:18","icon":"http://chart.apis.google.com/chart?chst=d_map_pin_letter&chld=50|FF0000|000000"}},
{"geometry":{"coordinates":[106.523285,10.9477183333333],"type":"Point"},"id":51,"type":"Feature","properties":{"date":"2016-10-08 08:54:38","icon":"http://chart.apis.google.com/chart?chst=d_map_pin_letter&chld=51|FF0000|000000"}},
{"geometry":{"coordinates":[106.52339,10.9476716666667],"type":"Point"},"id":52,"type":"Feature","properties":{"date":"2016-10-08 08:54:42","icon":"http://chart.apis.google.com/chart?chst=d_map_pin_letter&chld=52|FF0000|000000"}},
{"geometry":{"coordinates":[106.52449,10.94695],"type":"Point"},"id":53,"type":"Feature","properties":{"date":"2016-10-08 08:55:02","icon":"http://chart.apis.google.com/chart?chst=d_map_pin_letter&chld=53|FF0000|000000"}},
{"geometry":{"coordinates":[106.526196666667,10.9460433333333],"type":"Point"},"id":54,"type":"Feature","properties":{"date":"2016-10-08 08:55:22","icon":"http://chart.apis.google.com/chart?chst=d_map_pin_letter&chld=54|FF0000|000000"}},
{"geometry":{"coordinates":[106.528048333333,10.9451516666667],"type":"Point"},"id":55,"type":"Feature","properties":{"date":"2016-10-08 08:55:42","icon":"http://chart.apis.google.com/chart?chst=d_map_pin_letter&chld=55|FF0000|000000"}},
{"geometry":{"coordinates":[106.530011666667,10.9442083333333],"type":"Point"},"id":56,"type":"Feature","properties":{"date":"2016-10-08 08:56:02","icon":"http://chart.apis.google.com/chart?chst=d_map_pin_letter&chld=56|FF0000|000000"}},
{"geometry":{"coordinates":[106.531786666667,10.9433683333333],"type":"Point"},"id":57,"type":"Feature","properties":{"date":"2016-10-08 08:56:22","icon":"http://chart.apis.google.com/chart?chst=d_map_pin_letter&chld=57|FF0000|000000"}},
{"geometry":{"coordinates":[106.533521666667,10.94252],"type":"Point"},"id":58,"type":"Feature","properties":{"date":"2016-10-08 08:56:42","icon":"http://chart.apis.google.com/chart?chst=d_map_pin_letter&chld=58|FF0000|000000"}},
{"geometry":{"coordinates":[106.534301666667,10.942135],"type":"Point"},"id":59,"type":"Feature","properties":{"date":"2016-10-08 08:57:02","icon":"http://chart.apis.google.com/chart?chst=d_map_pin_letter&chld=59|FF0000|000000"}},
{"geometry":{"coordinates":[106.53607,10.9412816666667],"type":"Point"},"id":60,"type":"Feature","properties":{"date":"2016-10-08 08:57:22","icon":"http://chart.apis.google.com/chart?chst=d_map_pin_letter&chld=60|FF0000|000000"}},
{"geometry":{"coordinates":[106.536838333333,10.9409183333333],"type":"Point"},"id":61,"type":"Feature","properties":{"date":"2016-10-08 08:57:42","icon":"http://chart.apis.google.com/chart?chst=d_map_pin_letter&chld=61|FF0000|000000"}},
{"geometry":{"coordinates":[106.538675,10.940025],"type":"Point"},"id":62,"type":"Feature","properties":{"date":"2016-10-08 08:58:02","icon":"http://chart.apis.google.com/chart?chst=d_map_pin_letter&chld=62|FF0000|000000"}},
{"geometry":{"coordinates":[106.54053,10.939115],"type":"Point"},"id":63,"type":"Feature","properties":{"date":"2016-10-08 08:58:22","icon":"http://chart.apis.google.com/chart?chst=d_map_pin_letter&chld=63|FF0000|000000"}},
{"geometry":{"coordinates":[106.540651666667,10.9390533333333],"type":"Point"},"id":64,"type":"Feature","properties":{"date":"2016-10-08 08:58:30","icon":"http://chart.apis.google.com/chart?chst=d_map_pin_letter&chld=64|FF0000|000000"}},
{"geometry":{"coordinates":[106.540651666667,10.9390533333333],"type":"Point"},"id":65,"type":"Feature","properties":{"date":"2016-10-08 08:58:50","icon":"http://chart.apis.google.com/chart?chst=d_map_pin_letter&chld=65|FF0000|000000"}},
{"geometry":{"coordinates":[106.540796666667,10.9389866666667],"type":"Point"},"id":66,"type":"Feature","properties":{"date":"2016-10-08 08:59:10","icon":"http://chart.apis.google.com/chart?chst=d_map_pin_letter&chld=66|FF0000|000000"}},
{"geometry":{"coordinates":[106.542405,10.9382233333333],"type":"Point"},"id":67,"type":"Feature","properties":{"date":"2016-10-08 08:59:30","icon":"http://chart.apis.google.com/chart?chst=d_map_pin_letter&chld=67|FF0000|000000"}},
{"geometry":{"coordinates":[106.545226666667,10.9368666666667],"type":"Point"},"id":68,"type":"Feature","properties":{"date":"2016-10-08 08:59:50","icon":"http://chart.apis.google.com/chart?chst=d_map_pin_letter&chld=68|FF0000|000000"}},
{"geometry":{"coordinates":[106.548176666667,10.93544],"type":"Point"},"id":69,"type":"Feature","properties":{"date":"2016-10-08 09:00:10","icon":"http://chart.apis.google.com/chart?chst=d_map_pin_letter&chld=69|FF0000|000000"}},
{"geometry":{"coordinates":[106.54976,10.93463],"type":"Point"},"id":70,"type":"Feature","properties":{"date":"2016-10-08 09:00:30","icon":"http://chart.apis.google.com/chart?chst=d_map_pin_letter&chld=70|FF0000|000000"}},
{"geometry":{"coordinates":[106.549928333333,10.9345166666667],"type":"Point"},"id":71,"type":"Feature","properties":{"date":"2016-10-08 09:00:36","icon":"http://chart.apis.google.com/chart?chst=d_map_pin_letter&chld=71|FF0000|000000"}},
{"geometry":{"coordinates":[106.549995,10.9344683333333],"type":"Point"},"id":72,"type":"Feature","properties":{"date":"2016-10-08 09:00:43","icon":"http://chart.apis.google.com/chart?chst=d_map_pin_letter&chld=72|FF0000|000000"}},
{"geometry":{"coordinates":[106.5516,10.9333016666667],"type":"Point"},"id":73,"type":"Feature","properties":{"date":"2016-10-08 09:01:03","icon":"http://chart.apis.google.com/chart?chst=d_map_pin_letter&chld=73|FF0000|000000"}},
{"geometry":{"coordinates":[106.552116666667,10.9327566666667],"type":"Point"},"id":74,"type":"Feature","properties":{"date":"2016-10-08 09:01:09","icon":"http://chart.apis.google.com/chart?chst=d_map_pin_letter&chld=74|FF0000|000000"}},
{"geometry":{"coordinates":[106.552815,10.9319583333333],"type":"Point"},"id":75,"type":"Feature","properties":{"date":"2016-10-08 09:01:24","icon":"http://chart.apis.google.com/chart?chst=d_map_pin_letter&chld=75|FF0000|000000"}},
{"geometry":{"coordinates":[106.552888333333,10.931875],"type":"Point"},"id":76,"type":"Feature","properties":{"date":"2016-10-08 09:01:33","icon":"http://chart.apis.google.com/chart?chst=d_map_pin_letter&chld=76|FF0000|000000"}},
{"geometry":{"coordinates":[106.554143333333,10.9305483333333],"type":"Point"},"id":77,"type":"Feature","properties":{"date":"2016-10-08 09:01:53","icon":"http://chart.apis.google.com/chart?chst=d_map_pin_letter&chld=77|FF0000|000000"}},
{"geometry":{"coordinates":[106.5556,10.928725],"type":"Point"},"id":78,"type":"Feature","properties":{"date":"2016-10-08 09:02:13","icon":"http://chart.apis.google.com/chart?chst=d_map_pin_letter&chld=78|FF0000|000000"}},
{"geometry":{"coordinates":[106.556423333333,10.9275216666667],"type":"Point"},"id":79,"type":"Feature","properties":{"date":"2016-10-08 09:02:33","icon":"http://chart.apis.google.com/chart?chst=d_map_pin_letter&chld=79|FF0000|000000"}},
{"geometry":{"coordinates":[106.55647,10.92746],"type":"Point"},"id":80,"type":"Feature","properties":{"date":"2016-10-08 09:02:38","icon":"http://chart.apis.google.com/chart?chst=d_map_pin_letter&chld=80|FF0000|000000"}},
{"geometry":{"coordinates":[106.556535,10.92736],"type":"Point"},"id":81,"type":"Feature","properties":{"date":"2016-10-08 09:02:57","icon":"http://chart.apis.google.com/chart?chst=d_map_pin_letter&chld=81|FF0000|000000"}},
{"geometry":{"coordinates":[106.556778333333,10.9269233333333],"type":"Point"},"id":82,"type":"Feature","properties":{"date":"2016-10-08 09:03:07","icon":"http://chart.apis.google.com/chart?chst=d_map_pin_letter&chld=82|FF0000|000000"}},
{"geometry":{"coordinates":[106.556875,10.92678],"type":"Point"},"id":83,"type":"Feature","properties":{"date":"2016-10-08 09:03:13","icon":"http://chart.apis.google.com/chart?chst=d_map_pin_letter&chld=83|FF0000|000000"}},
{"geometry":{"coordinates":[106.556875,10.92678],"type":"Point"},"id":84,"type":"Feature","properties":{"date":"2016-10-08 09:03:15","icon":"http://chart.apis.google.com/chart?chst=d_map_pin_letter&chld=84|FF0000|000000"}},
{"geometry":{"coordinates":[106.556906666667,10.9267333333333],"type":"Point"},"id":85,"type":"Feature","properties":{"date":"2016-10-08 09:03:29","icon":"http://chart.apis.google.com/chart?chst=d_map_pin_letter&chld=85|FF0000|000000"}},
{"geometry":{"coordinates":[106.55723,10.92629],"type":"Point"},"id":86,"type":"Feature","properties":{"date":"2016-10-08 09:03:43","icon":"http://chart.apis.google.com/chart?chst=d_map_pin_letter&chld=86|FF0000|000000"}},
{"geometry":{"coordinates":[106.55728,10.926205],"type":"Point"},"id":87,"type":"Feature","properties":{"date":"2016-10-08 09:03:46","icon":"http://chart.apis.google.com/chart?chst=d_map_pin_letter&chld=87|FF0000|000000"}},
{"geometry":{"coordinates":[106.558308333333,10.92483],"type":"Point"},"id":88,"type":"Feature","properties":{"date":"2016-10-08 09:04:06","icon":"http://chart.apis.google.com/chart?chst=d_map_pin_letter&chld=88|FF0000|000000"}},
{"geometry":{"coordinates":[106.56015,10.9222016666667],"type":"Point"},"id":89,"type":"Feature","properties":{"date":"2016-10-08 09:04:26","icon":"http://chart.apis.google.com/chart?chst=d_map_pin_letter&chld=89|FF0000|000000"}},
{"geometry":{"coordinates":[106.562218333333,10.919255],"type":"Point"},"id":90,"type":"Feature","properties":{"date":"2016-10-08 09:04:46","icon":"http://chart.apis.google.com/chart?chst=d_map_pin_letter&chld=90|FF0000|000000"}},
{"geometry":{"coordinates":[106.563771666667,10.917035],"type":"Point"},"id":91,"type":"Feature","properties":{"date":"2016-10-08 09:05:06","icon":"http://chart.apis.google.com/chart?chst=d_map_pin_letter&chld=91|FF0000|000000"}},
{"geometry":{"coordinates":[106.564326666667,10.9161916666667],"type":"Point"},"id":92,"type":"Feature","properties":{"date":"2016-10-08 09:05:19","icon":"http://chart.apis.google.com/chart?chst=d_map_pin_letter&chld=92|FF0000|000000"}},
{"geometry":{"coordinates":[106.564413333333,10.9160933333333],"type":"Point"},"id":93,"type":"Feature","properties":{"date":"2016-10-08 09:05:23","icon":"http://chart.apis.google.com/chart?chst=d_map_pin_letter&chld=93|FF0000|000000"}},
{"geometry":{"coordinates":[106.565595,10.91443],"type":"Point"},"id":94,"type":"Feature","properties":{"date":"2016-10-08 09:05:43","icon":"http://chart.apis.google.com/chart?chst=d_map_pin_letter&chld=94|FF0000|000000"}},
{"geometry":{"coordinates":[106.567271666667,10.9120183333333],"type":"Point"},"id":95,"type":"Feature","properties":{"date":"2016-10-08 09:06:03","icon":"http://chart.apis.google.com/chart?chst=d_map_pin_letter&chld=95|FF0000|000000"}},
{"geometry":{"coordinates":[106.568816666667,10.9098466666667],"type":"Point"},"id":96,"type":"Feature","properties":{"date":"2016-10-08 09:06:23","icon":"http://chart.apis.google.com/chart?chst=d_map_pin_letter&chld=96|FF0000|000000"}},
{"geometry":{"coordinates":[106.570175,10.90788],"type":"Point"},"id":97,"type":"Feature","properties":{"date":"2016-10-08 09:06:43","icon":"http://chart.apis.google.com/chart?chst=d_map_pin_letter&chld=97|FF0000|000000"}},
{"geometry":{"coordinates":[106.571553333333,10.90592],"type":"Point"},"id":98,"type":"Feature","properties":{"date":"2016-10-08 09:07:03","icon":"http://chart.apis.google.com/chart?chst=d_map_pin_letter&chld=98|FF0000|000000"}},
{"geometry":{"coordinates":[106.57276,10.9041933333333],"type":"Point"},"id":99,"type":"Feature","properties":{"date":"2016-10-08 09:07:23","icon":"http://chart.apis.google.com/chart?chst=d_map_pin_letter&chld=99|FF0000|000000"}},
{"geometry":{"coordinates":[106.573978333333,10.9025083333333],"type":"Point"},"id":100,"type":"Feature","properties":{"date":"2016-10-08 09:07:43","icon":"http://chart.apis.google.com/chart?chst=d_map_pin_letter&chld=100|FF0000|000000"}},
{"geometry":{"coordinates":[106.575095,10.9007616666667],"type":"Point"},"id":101,"type":"Feature","properties":{"date":"2016-10-08 09:08:03","icon":"http://chart.apis.google.com/chart?chst=d_map_pin_letter&chld=101|FF0000|000000"}},
{"geometry":{"coordinates":[106.575983333333,10.8995566666667],"type":"Point"},"id":102,"type":"Feature","properties":{"date":"2016-10-08 09:08:23","icon":"http://chart.apis.google.com/chart?chst=d_map_pin_letter&chld=102|FF0000|000000"}},
{"geometry":{"coordinates":[106.577226666667,10.8978016666667],"type":"Point"},"id":103,"type":"Feature","properties":{"date":"2016-10-08 09:08:43","icon":"http://chart.apis.google.com/chart?chst=d_map_pin_letter&chld=103|FF0000|000000"}},
{"geometry":{"coordinates":[106.578431666667,10.8960366666667],"type":"Point"},"id":104,"type":"Feature","properties":{"date":"2016-10-08 09:09:03","icon":"http://chart.apis.google.com/chart?chst=d_map_pin_letter&chld=104|FF0000|000000"}},
{"geometry":{"coordinates":[106.578481666667,10.8959716666667],"type":"Point"},"id":105,"type":"Feature","properties":{"date":"2016-10-08 09:09:09","icon":"http://chart.apis.google.com/chart?chst=d_map_pin_letter&chld=105|FF0000|000000"}},
{"geometry":{"coordinates":[106.578561666667,10.8958916666667],"type":"Point"},"id":106,"type":"Feature","properties":{"date":"2016-10-08 09:09:12","icon":"http://chart.apis.google.com/chart?chst=d_map_pin_letter&chld=106|FF0000|000000"}},
{"geometry":{"coordinates":[106.579795,10.8941316666667],"type":"Point"},"id":107,"type":"Feature","properties":{"date":"2016-10-08 09:09:33","icon":"http://chart.apis.google.com/chart?chst=d_map_pin_letter&chld=107|FF0000|000000"}},
{"geometry":{"coordinates":[106.581018333333,10.8922883333333],"type":"Point"},"id":108,"type":"Feature","properties":{"date":"2016-10-08 09:09:53","icon":"http://chart.apis.google.com/chart?chst=d_map_pin_letter&chld=108|FF0000|000000"}},
{"geometry":{"coordinates":[106.581056666667,10.89223],"type":"Point"},"id":109,"type":"Feature","properties":{"date":"2016-10-08 09:09:57","icon":"http://chart.apis.google.com/chart?chst=d_map_pin_letter&chld=109|FF0000|000000"}},
{"geometry":{"coordinates":[106.581151666667,10.8921316666667],"type":"Point"},"id":110,"type":"Feature","properties":{"date":"2016-10-08 09:10:02","icon":"http://chart.apis.google.com/chart?chst=d_map_pin_letter&chld=110|FF0000|000000"}},
{"geometry":{"coordinates":[106.582355,10.8905266666667],"type":"Point"},"id":111,"type":"Feature","properties":{"date":"2016-10-08 09:10:22","icon":"http://chart.apis.google.com/chart?chst=d_map_pin_letter&chld=111|FF0000|000000"}},
{"geometry":{"coordinates":[106.584143333333,10.887955],"type":"Point"},"id":112,"type":"Feature","properties":{"date":"2016-10-08 09:10:42","icon":"http://chart.apis.google.com/chart?chst=d_map_pin_letter&chld=112|FF0000|000000"}},
{"geometry":{"coordinates":[106.585718333333,10.8857516666667],"type":"Point"},"id":113,"type":"Feature","properties":{"date":"2016-10-08 09:11:02","icon":"http://chart.apis.google.com/chart?chst=d_map_pin_letter&chld=113|FF0000|000000"}},
{"geometry":{"coordinates":[106.58607,10.8851983333333],"type":"Point"},"id":114,"type":"Feature","properties":{"date":"2016-10-08 09:11:21","icon":"http://chart.apis.google.com/chart?chst=d_map_pin_letter&chld=114|FF0000|000000"}},
{"geometry":{"coordinates":[106.58607,10.8851983333333],"type":"Point"},"id":115,"type":"Feature","properties":{"date":"2016-10-08 09:11:41","icon":"http://chart.apis.google.com/chart?chst=d_map_pin_letter&chld=115|FF0000|000000"}},
{"geometry":{"coordinates":[106.586158333333,10.88505],"type":"Point"},"id":116,"type":"Feature","properties":{"date":"2016-10-08 09:11:44","icon":"http://chart.apis.google.com/chart?chst=d_map_pin_letter&chld=116|FF0000|000000"}},
{"geometry":{"coordinates":[106.586846666667,10.88406],"type":"Point"},"id":117,"type":"Feature","properties":{"date":"2016-10-08 09:12:04","icon":"http://chart.apis.google.com/chart?chst=d_map_pin_letter&chld=117|FF0000|000000"}},
{"geometry":{"coordinates":[106.588081666667,10.8822866666667],"type":"Point"},"id":118,"type":"Feature","properties":{"date":"2016-10-08 09:12:24","icon":"http://chart.apis.google.com/chart?chst=d_map_pin_letter&chld=118|FF0000|000000"}},
{"geometry":{"coordinates":[106.589413333333,10.880375],"type":"Point"},"id":119,"type":"Feature","properties":{"date":"2016-10-08 09:12:44","icon":"http://chart.apis.google.com/chart?chst=d_map_pin_letter&chld=119|FF0000|000000"}},
{"geometry":{"coordinates":[106.590546666667,10.878745],"type":"Point"},"id":120,"type":"Feature","properties":{"date":"2016-10-08 09:13:04","icon":"http://chart.apis.google.com/chart?chst=d_map_pin_letter&chld=120|FF0000|000000"}},
{"geometry":{"coordinates":[106.59092,10.8781866666667],"type":"Point"},"id":121,"type":"Feature","properties":{"date":"2016-10-08 09:13:19","icon":"http://chart.apis.google.com/chart?chst=d_map_pin_letter&chld=121|FF0000|000000"}},
{"geometry":{"coordinates":[106.59092,10.8781866666667],"type":"Point"},"id":122,"type":"Feature","properties":{"date":"2016-10-08 09:13:39","icon":"http://chart.apis.google.com/chart?chst=d_map_pin_letter&chld=122|FF0000|000000"}},
{"geometry":{"coordinates":[106.591011666667,10.878095],"type":"Point"},"id":123,"type":"Feature","properties":{"date":"2016-10-08 09:13:47","icon":"http://chart.apis.google.com/chart?chst=d_map_pin_letter&chld=123|FF0000|000000"}},
{"geometry":{"coordinates":[106.591936666667,10.876845],"type":"Point"},"id":124,"type":"Feature","properties":{"date":"2016-10-08 09:14:07","icon":"http://chart.apis.google.com/chart?chst=d_map_pin_letter&chld=124|FF0000|000000"}},
{"geometry":{"coordinates":[106.593166666667,10.8751116666667],"type":"Point"},"id":125,"type":"Feature","properties":{"date":"2016-10-08 09:14:27","icon":"http://chart.apis.google.com/chart?chst=d_map_pin_letter&chld=125|FF0000|000000"}},
{"geometry":{"coordinates":[106.594513333333,10.8732033333333],"type":"Point"},"id":126,"type":"Feature","properties":{"date":"2016-10-08 09:14:47","icon":"http://chart.apis.google.com/chart?chst=d_map_pin_letter&chld=126|FF0000|000000"}},
{"geometry":{"coordinates":[106.59575,10.8713883333333],"type":"Point"},"id":127,"type":"Feature","properties":{"date":"2016-10-08 09:15:07","icon":"http://chart.apis.google.com/chart?chst=d_map_pin_letter&chld=127|FF0000|000000"}},
{"geometry":{"coordinates":[106.596761666667,10.8699733333333],"type":"Point"},"id":128,"type":"Feature","properties":{"date":"2016-10-08 09:15:27","icon":"http://chart.apis.google.com/chart?chst=d_map_pin_letter&chld=128|FF0000|000000"}},
{"geometry":{"coordinates":[106.596796666667,10.869915],"type":"Point"},"id":129,"type":"Feature","properties":{"date":"2016-10-08 09:15:31","icon":"http://chart.apis.google.com/chart?chst=d_map_pin_letter&chld=129|FF0000|000000"}},
{"geometry":{"coordinates":[106.596858333333,10.8698316666667],"type":"Point"},"id":130,"type":"Feature","properties":{"date":"2016-10-08 09:15:41","icon":"http://chart.apis.google.com/chart?chst=d_map_pin_letter&chld=130|FF0000|000000"}},
{"geometry":{"coordinates":[106.597913333333,10.8684366666667],"type":"Point"},"id":131,"type":"Feature","properties":{"date":"2016-10-08 09:16:01","icon":"http://chart.apis.google.com/chart?chst=d_map_pin_letter&chld=131|FF0000|000000"}},
{"geometry":{"coordinates":[106.599305,10.8664783333333],"type":"Point"},"id":132,"type":"Feature","properties":{"date":"2016-10-08 09:16:21","icon":"http://chart.apis.google.com/chart?chst=d_map_pin_letter&chld=132|FF0000|000000"}},
{"geometry":{"coordinates":[106.60043,10.8649433333333],"type":"Point"},"id":133,"type":"Feature","properties":{"date":"2016-10-08 09:16:41","icon":"http://chart.apis.google.com/chart?chst=d_map_pin_letter&chld=133|FF0000|000000"}},
{"geometry":{"coordinates":[106.601676666667,10.86311],"type":"Point"},"id":134,"type":"Feature","properties":{"date":"2016-10-08 09:17:01","icon":"http://chart.apis.google.com/chart?chst=d_map_pin_letter&chld=134|FF0000|000000"}},
{"geometry":{"coordinates":[106.602588333333,10.861745],"type":"Point"},"id":135,"type":"Feature","properties":{"date":"2016-10-08 09:17:21","icon":"http://chart.apis.google.com/chart?chst=d_map_pin_letter&chld=135|FF0000|000000"}},
{"geometry":{"coordinates":[106.603321666667,10.86073],"type":"Point"},"id":136,"type":"Feature","properties":{"date":"2016-10-08 09:17:41","icon":"http://chart.apis.google.com/chart?chst=d_map_pin_letter&chld=136|FF0000|000000"}},
{"geometry":{"coordinates":[106.604316666667,10.859415],"type":"Point"},"id":137,"type":"Feature","properties":{"date":"2016-10-08 09:18:01","icon":"http://chart.apis.google.com/chart?chst=d_map_pin_letter&chld=137|FF0000|000000"}},
{"geometry":{"coordinates":[106.605363333333,10.85794],"type":"Point"},"id":138,"type":"Feature","properties":{"date":"2016-10-08 09:18:21","icon":"http://chart.apis.google.com/chart?chst=d_map_pin_letter&chld=138|FF0000|000000"}},
{"geometry":{"coordinates":[106.606128333333,10.85677],"type":"Point"},"id":139,"type":"Feature","properties":{"date":"2016-10-08 09:18:41","icon":"http://chart.apis.google.com/chart?chst=d_map_pin_letter&chld=139|FF0000|000000"}},
{"geometry":{"coordinates":[106.606738333333,10.855825],"type":"Point"},"id":140,"type":"Feature","properties":{"date":"2016-10-08 09:19:01","icon":"http://chart.apis.google.com/chart?chst=d_map_pin_letter&chld=140|FF0000|000000"}},
{"geometry":{"coordinates":[106.606963333333,10.8555816666667],"type":"Point"},"id":141,"type":"Feature","properties":{"date":"2016-10-08 09:19:16","icon":"http://chart.apis.google.com/chart?chst=d_map_pin_letter&chld=141|FF0000|000000"}},
{"geometry":{"coordinates":[106.606963333333,10.8555816666667],"type":"Point"},"id":142,"type":"Feature","properties":{"date":"2016-10-08 09:19:36","icon":"http://chart.apis.google.com/chart?chst=d_map_pin_letter&chld=142|FF0000|000000"}},
{"geometry":{"coordinates":[106.607036666667,10.855495],"type":"Point"},"id":143,"type":"Feature","properties":{"date":"2016-10-08 09:19:49","icon":"http://chart.apis.google.com/chart?chst=d_map_pin_letter&chld=143|FF0000|000000"}},
{"geometry":{"coordinates":[106.60778,10.854325],"type":"Point"},"id":144,"type":"Feature","properties":{"date":"2016-10-08 09:20:09","icon":"http://chart.apis.google.com/chart?chst=d_map_pin_letter&chld=144|FF0000|000000"}},
{"geometry":{"coordinates":[106.609021666667,10.8523683333333],"type":"Point"},"id":145,"type":"Feature","properties":{"date":"2016-10-08 09:20:29","icon":"http://chart.apis.google.com/chart?chst=d_map_pin_letter&chld=145|FF0000|000000"}},
{"geometry":{"coordinates":[106.610393333333,10.8502716666667],"type":"Point"},"id":146,"type":"Feature","properties":{"date":"2016-10-08 09:20:49","icon":"http://chart.apis.google.com/chart?chst=d_map_pin_letter&chld=146|FF0000|000000"}},
{"geometry":{"coordinates":[106.612108333333,10.84758],"type":"Point"},"id":147,"type":"Feature","properties":{"date":"2016-10-08 09:21:45","icon":"http://chart.apis.google.com/chart?chst=d_map_pin_letter&chld=147|FF0000|000000"}},
{"geometry":{"coordinates":[106.61213,10.8475466666667],"type":"Point"},"id":148,"type":"Feature","properties":{"date":"2016-10-08 09:21:46","icon":"http://chart.apis.google.com/chart?chst=d_map_pin_letter&chld=148|FF0000|000000"}},
{"geometry":{"coordinates":[106.612503333333,10.8468966666667],"type":"Point"},"id":149,"type":"Feature","properties":{"date":"2016-10-08 09:22:06","icon":"http://chart.apis.google.com/chart?chst=d_map_pin_letter&chld=149|FF0000|000000"}},
{"geometry":{"coordinates":[106.613331666667,10.8456533333333],"type":"Point"},"id":150,"type":"Feature","properties":{"date":"2016-10-08 09:22:26","icon":"http://chart.apis.google.com/chart?chst=d_map_pin_letter&chld=150|FF0000|000000"}},
{"geometry":{"coordinates":[106.613678333333,10.845055],"type":"Point"},"id":151,"type":"Feature","properties":{"date":"2016-10-08 09:22:39","icon":"http://chart.apis.google.com/chart?chst=d_map_pin_letter&chld=151|FF0000|000000"}},
{"geometry":{"coordinates":[106.613545,10.84345],"type":"Point"},"id":152,"type":"Feature","properties":{"date":"2016-10-08 09:25:12","icon":"http://chart.apis.google.com/chart?chst=d_map_pin_letter&chld=152|FF0000|000000"}}
]}